Workbook

Sheet Dashboard
B1: CoW Swap — QA Test Checklist
B2: swap.cow.fi | Version 1.0 | May 2026
B4: TEST EXECUTION SUMMARY
B5: Category | C5: Total | D5: Pass | E5: Fail | F5: Blocked | G5: % Pass
B6: Wallet Connection | C6: =COUNTA(WalletConnection!H5:H200) -> 17 | D6: =COUNTIF(WalletConnection!H5:H200,"Pass") -> 0 | E6: =COUNTIF(WalletConnection!H5:H200,"Fail") -> 0 | F6: =COUNTIF(WalletConnection!H5:H200,"Blocked") -> 0 | G6: =IF(C6=0,"-",D6/C6) -> 0
B7: Safe Wallet | C7: =COUNTA(SafeWallet!H5:H200) -> 16 | D7: =COUNTIF(SafeWallet!H5:H200,"Pass") -> 0 | E7: =COUNTIF(SafeWallet!H5:H200,"Fail") -> 0 | F7: =COUNTIF(SafeWallet!H5:H200,"Blocked") -> 0 | G7: =IF(C7=0,"-",D7/C7) -> 0
B8: Smart Accounts | C8: =COUNTA(SmartAccounts!H5:H200) -> 12 | D8: =COUNTIF(SmartAccounts!H5:H200,"Pass") -> 0 | E8: =COUNTIF(SmartAccounts!H5:H200,"Fail") -> 0 | F8: =COUNTIF(SmartAccounts!H5:H200,"Blocked") -> 0 | G8: =IF(C8=0,"-",D8/C8) -> 0
B9: Market Orders (Swap) | C9: =COUNTA(MarketOrders!H5:H200) -> 79 | D9: =COUNTIF(MarketOrders!H5:H200,"Pass") -> 0 | E9: =COUNTIF(MarketOrders!H5:H200,"Fail") -> 0 | F9: =COUNTIF(MarketOrders!H5:H200,"Blocked") -> 0 | G9: =IF(C9=0,"-",D9/C9) -> 0
B10: Limit Orders | C10: =COUNTA(LimitOrders!H5:H200) -> 66 | D10: =COUNTIF(LimitOrders!H5:H199,"Pass") -> 0 | E10: =COUNTIF(LimitOrders!H5:H199,"Fail") -> 0 | F10: =COUNTIF(LimitOrders!H5:H199,"Blocked") -> 0 | G10: =IF(C10=0,"-",D10/C10) -> 0
B11: TWAP Orders | C11: =COUNTA(TWAPOrders!H5:H201) -> 57 | D11: =COUNTIF(TWAPOrders!H5:H195,"Pass") -> 0 | E11: =COUNTIF(TWAPOrders!H5:H195,"Fail") -> 0 | F11: =COUNTIF(TWAPOrders!H5:H195,"Blocked") -> 0 | G11: =IF(C11=0,"-",D11/C11) -> 0
B12: Cross-Chain Swaps | C12: =COUNTA(CrossChain!H5:H195) -> 31 | D12: =COUNTIF(CrossChain!H5:H195,"Pass") -> 0 | E12: =COUNTIF(CrossChain!H5:H195,"Fail") -> 0 | F12: =COUNTIF(CrossChain!H5:H195,"Blocked") -> 0 | G12: =IF(C12=0,"-",D12/C12) -> 0
B13: UI / UX | C13: =COUNTA(UIUX!H5:H200) -> 23 | D13: =COUNTIF(UIUX!H5:H200,"Pass") -> 0 | E13: =COUNTIF(UIUX!H5:H200,"Fail") -> 0 | F13: =COUNTIF(UIUX!H5:H200,"Blocked") -> 0 | G13: =IF(C13=0,"-",D13/C13) -> 0
B14: Hooks | C14: =COUNTA(Hooks!H5:H200) -> 7 | D14: =COUNTIF(Hooks!H5:H200,"Pass") -> 0 | E14: =COUNTIF(Hooks!H5:H200,"Fail") -> 0 | F14: =COUNTIF(Hooks!H5:H200,"Blocked") -> 0 | G14: =IF(C14=0,"-",D14/C14) -> 0
B15: Account Pages | C15: =COUNTA(AccountOverview!H5:H212) -> 35 | D15: =COUNTIF(AccountOverview!H5:H212,"Pass") -> 0 | E15: =COUNTIF(AccountOverview!H5:H212,"Fail") -> 0 | F15: =COUNTIF(AccountOverview!H5:H212,"Blocked") -> 0 | G15: =IF(C15=0,"-",D15/C15) -> 0
B16: RWA (Ondo & xStocks) | C16: =COUNTA(RWA!H5:H200) -> 19 | D16: =COUNTIF(RWA!H5:H200,"Pass") -> 0 | E16: =COUNTIF(RWA!H5:H200,"Fail") -> 0 | F16: =COUNTIF(RWA!H5:H200,"Blocked") -> 0 | G16: =IFERROR(D16/C16,0) -> 0
B17: TOTAL | C17: =SUM(C6:C16) -> 362 | D17: =SUM(D6:D16) -> 0 | E17: =SUM(E6:E16) -> 0 | F17: =SUM(F6:F16) -> 0 | G17: =IF(C17=0,"-",D17/C17) -> 0
B19: STATUS LEGEND
B20: ✅ Pass
B21: ❌ Fail
B22: ⏸ Blocked
B23: ⬜ Not Run

Sheet WalletConnection
A1: Wallet Connection Tests
A2: CoW Swap | swap.cow.fi | WalletConnection
A4: ID | B4: Test Name | C4: Priority | D4: Type | E4: Preconditions | F4: Test Steps | G4: Expected Result | H4: Status | I4: Notes / Defect ID
A5: WC-01 | B5: Connect MetaMask wallet | C5: High | D5: Functional | E5: MetaMask installed & unlocked | F5: 1. Open swap.cow.fi 2. Click 'Connect Wallet' 3. Select MetaMask 4. Approve connection in MetaMask popup | G5: 1. Wallet address shown in header 2. correct network displayed | H5: Not Run
A6: WC-02 | B6: Connect WalletConnect | C6: High | D6: Functional | E6: Mobile wallet with WalletConnect | F6: 1. Click 'Connect Wallet' 2. Select WalletConnect 3. Scan QR with mobile wallet | G6: 1. Wallet connected 2. address shown correctly | H6: Not Run
A7: WC-03 | B7: Connect Rabby wallet | C7: Medium | D7: Functional | E7: Rabby extension installed | F7: 1. Click 'Connect Wallet' 2. Select Rabby 3. Approve | G7: Wallet connected successfully | H7: Not Run
A8: WC-04 | B8: Connect hardware wallet via MetaMask | C8: Medium | D8: Functional | E8: Trezor / Ledger linked to MetaMask | F8: 1. Connect MetaMask (hardware) 2. Select hardware account | G8: 1. Hardware wallet address shown 2. EIP-712 signing prompt works | H8: Not Run
A9: WC-05 | B9: Switch network while connected | C9: High | D9: Functional | E9: Wallet connected on Ethereum Mainnet | F9: 1. Switch to Gnosis Chain in wallet 2. Observe UI update | G9: 1. UI reflects new network 2. token list updates accordingly | H9: Not Run
A10: WC-06 | B10: Disconnect wallet | C10: Medium | D10: Functional | E10: Wallet currently connected | F10: 1. Click wallet address 2. Select 'Disconnect' | G10: 1. Wallet disconnected 2. connect button restored | H10: Not Run
A11: WC-07 | B11: Session persistence on page reload | C11: Low | D11: Functional | E11: Wallet connected | F11: 1. Reload the page | G11: 1. Wallet remains connected 2. no re-auth required | H11: Not Run
A12: WC-08 | B12: Connect via mobile app (in-app browser) | C12: High | D12: Functional | E12: Mobile wallet app installed (e.g. MetaMask Mobile, Trust Wallet); mobile device | F12: 1. Open wallet app on mobile device 2. Navigate to the in-app browser (DApp browser) 3. Enter https://swap.cow.fi 4. Tap 'Connect Wallet' 5. Select the injected wallet option (should auto-detect mobile wallet) 6. Approve connection in wallet prompt | G12: 1. Wallet auto-detected as injected provider 2. address shown in header 3. correct chain displayed 4. swap UI fully functional in mobile in-app browser | H12: Not Run
A13: WC-09 | B13: Connect via mobile app — WalletConnect fallback | C13: Medium | D13: Functional | E13: Mobile device with wallet that supports WalletConnect v2 but does NOT inject a provider (e.g. opened in system browser, not in-app browser) | F13: 1. Open swap.cow.fi in mobile system browser (Safari / Chrome) 2. Tap 'Connect Wallet' 3. Select WalletConnect 4. Tap the deep-link / 'Open in wallet' button 5. Approve connection in the wallet app | G13: 1. WalletConnect session established via deep-link 2. wallet address shown 3. no duplicate connection prompts 4. session stable across mobile browser background/foreground cycles | H13: Not Run
A14: WC-10 | B14: Connect inside wallet's built-in browser (injected provider detection) | C14: High | D14: Functional | E14: Wallet with built-in DApp browser (MetaMask Mobile, Coinbase Wallet, Rabby Mobile); navigate to swap.cow.fi from within that browser | F14: 1. Open wallet app 2. Go to the built-in browser / DApp browser tab 3. Navigate to swap.cow.fi 4. Observe whether wallet is auto-detected 5. If not auto-detected, tap 'Connect Wallet' and confirm injected option is listed 6. Approve connection | G14: 1. window.ethereum injected correctly 2. wallet listed as first option 3. no WalletConnect QR shown unnecessarily 4. connection completes without leaving the browser view | H14: Not Run
A15: WC-11 | B15: Connect Safe via WalletConnect (external signer) | C15: High | D15: Functional | E15: Safe wallet deployed on target network; at least one signer device (desktop or mobile wallet with WC v2 support); Safe does NOT need to be used as Safe App | F15: 1. Open swap.cow.fi in a regular browser 2. Click 'Connect Wallet' 3. Select WalletConnect 4. Copy or scan the WC URI 5. In the Safe interface (app.safe.global), go to WalletConnect section and paste the URI 6. Approve the connection from Safe 7. Collect required signer approvals if threshold > 1 | G15: 1. Safe address (0x…) shown as connected wallet 2. UI recognises smart contract wallet 3. ERC-1271 signing used for order placement 4. TWAP / advanced order types accessible | H15: Not Run
A16: WC-12 | B16: Open CoW Swap inside Safe App (native Safe App integration) | C16: High | D16: Functional | E16: Safe wallet exists; access to app.safe.global or Safe mobile app | F16: 1. Log in to app.safe.global with Safe owner wallet 2. Navigate to Apps → Search for 'CoW Swap' 3. Open CoW Swap Safe App 4. Verify auto-connection (no manual connect step should be required) 5. Attempt a swap or limit order to confirm full functionality | G16: 1. CoW Swap loads inside Safe iframe 2. Safe address auto-connected 3. no extra connect step 4. TWAP tab visible and accessible 5. order signing routes through Safe transaction queue | H16: Not Run | I16: Also test in Safe mobile app if available
A17: WC-13 | B17: Multiple tabs — connection state isolation | C17: High | D17: Functional | E17: Desktop browser; wallet extension installed (e.g. MetaMask) | F17: 1. Open swap.cow.fi in Tab A; connect Wallet A 2. Open swap.cow.fi in Tab B (same browser, new tab) 3. In Tab B, connect a different account (switch account in MetaMask) 4. Switch back to Tab A and interact (e.g. refresh quote) 5. Repeat with one tab connected and one tab with no wallet | G17: 1. Each tab reflects its own connection state without corrupting the other 2. Tab A does not silently adopt Tab B's account change 3. wallet account changes propagate correctly only to the active/focused tab OR consistently to all tabs per wallet extension behaviour | H17: Not Run | I17: Document actual wallet extension behaviour (MetaMask broadcasts accountsChanged to all tabs — this is expected and should be noted, not flagged as a bug)
A18: WC-14 | B18: Multiple tabs — no duplicate connection prompts | C18: Medium | D18: Functional | E18: swap.cow.fi open in 2+ tabs simultaneously | F18: 1. Open swap.cow.fi in Tab A and Tab B 2. In Tab A, click 'Connect Wallet' and begin connection flow 3. Switch to Tab B without completing connection in Tab A 4. Observe Tab B's state 5. Complete connection in Tab A; verify Tab B updates appropriately | G18: 1. Tab B does not launch its own unsolicited connection prompt 2. completing connection in Tab A does not leave Tab B in a broken/mixed state 3. no JS errors in console related to provider conflicts | H18: Not Run
A19: WC-15 | B19: Account modal: connected wallet address displayed correctly | C19: High | D19: Functional | E19: Wallet connected | F19: 1. Open account modal 2. Verify wallet address shown 3. Compare to wallet extension address | G19: 1. Full or truncated wallet address shown and matches connected wallet 2. ENS name shown if resolved 3. correct for all wallet types (EOA, Safe, MM Smart Account, Base SA) | H19: Not Run
A20: WC-16 | B20: Account modal: history shows last 10 orders | C20: Medium | D20: Functional | E20: Wallet connected | F20: 1. Open account modal | G20: 1. Up to last 10 orders shown 2. link to CoW Explorer provided for full history 3. orders show status (In Progress, Filled, Cancelled, Expired) 4. each order links to explorer detail page | H20: Not Run
A21: WC-17 | B21: Account modal: network switch updates displayed data | C21: Medium | D21: Functional | E21: Wallet connected on Ethereum Mainnet | F21: 1. View account overview on Mainnet 2. Switch wallet to Gnosis Chain 3. Observe account data refresh | G21: 1. Account data updates to reflect new chain 2. token balances, order history, and proxy info shown for the newly connected chain 3. no stale Mainnet data persists | H21: Not Run

Sheet SafeWallet
A1: Safe Wallet Tests
A2: CoW Swap | swap.cow.fi | SafeWallet
A4: ID | B4: Test Name | C4: Priority | D4: Type | E4: Preconditions | F4: Test Steps | G4: Expected Result | H4: Status | I4: Notes / Defect ID
A5: SW-01 | B5: Safe App: CoW Swap opens inside Safe — auto-connection | C5: High | D5: Functional | E5: Safe wallet exists on a supported chain; access to app.safe.global or Safe mobile app | F5: 1. Log in to app.safe.global with a Safe owner wallet 2. Navigate to Apps → search 'CoW Swap' 3. Open CoW Swap Safe App 4. Observe connection state — no manual connect step expected | G5: 1. CoW Swap loads inside Safe iframe 2. Safe address auto-connected 3. no 'Connect Wallet' prompt 4. Safe App License Fee (0.1%) shown in fee fields fior non-correlated assets | H5: Not Run | I5: This is the primary Safe integration path. Safe charges its own 0.1% fee when app is opened here correlated assets listed in https://cms.cow.fi/admin/content-manager/collection-types/api::correlated-token.correlated-token?page=1&pageSize=10&sort=name:ASC
A6: SW-02 | B6: Safe App: order signing routes through Safe tx queue | C6: High | D6: Functional | E6: CoW Swap open inside Safe App; Safe threshold ≥ 1 | F6: 1. Place a market swap order inside CoW Swap Safe App 2. Observe signing flow — should NOT open individual EOA wallet prompt 3. Verify new transaction appears in Safe transaction queue 4. Collect required signer signatures 5. Execute the transaction | G6: 1. Safe TX created in queue 2. order only submitted to CoW Protocol API after on-chain Safe TX executes 3. no off-chain EOA signature bypass 4. threshold satisfied before execution | H6: Not Run
A7: SW-03 | B7: Safe via WalletConnect — desktop Safe app (app.safe.global) | C7: High | D7: Functional | E7: Safe wallet deployed; access to app.safe.global; no Safe App used — connecting externally via WC | F7: 1. Open swap.cow.fi in a separate browser tab 2. Click 'Connect Wallet' → select WalletConnect 3. Copy the WC URI 4. In app.safe.global → WalletConnect section → paste URI 5. Approve connection from Safe desktop app 6. Return to swap.cow.fi | G7: 1. Safe address shown as connected wallet in CoW Swap 2. UI recognises SC wallet (ERC-1271 signing) 3. TWAP available if fallback handler installed 4. Safe App License Fee NOT applied (only applies inside Safe App iframe) 5. no gasless transactions (SC wallet) | H7: Not Run | I7: Key difference from SW-01: no Safe App fee; no gasless; orders still sign via Safe tx queue
A8: SW-04 | B8: Safe via WalletConnect — mobile Safe app | C8: High | D8: Functional | E8: Safe wallet; Safe mobile app installed; swap.cow.fi open in desktop browser | F8: 1. Open swap.cow.fi on desktop 2. Click 'Connect Wallet' → WalletConnect 3. Scan WC QR code with Safe mobile app 4. Approve connection in Safe mobile 5. Place a swap order on desktop 6. Approve the Safe TX in Safe mobile app (collect signatures) | G8: 1. Safe address connected 2. order placement triggers Safe TX in mobile app queue 3. all signers must approve via mobile 4. Safe App fee NOT applied 5. no gasless 6. signing is on-chain | H8: Not Run | I8: This type of connection does not support transactions bundling
A9: SW-05 | B9: Safe imported in Rabby wallet — connection and signing | C9: High | D9: Functional | E9: Rabby wallet extension installed; Safe wallet imported into Rabby (Rabby supports Safe as an account type) | F9: 1. In Rabby, switch to the imported Safe account 2. Open swap.cow.fi 3. Connect wallet — Rabby injected provider selected 4. Place a swap order 5. Observe signing flow in Rabby | G9: 1. Safe address shown as connected 2. Rabby handles signing on behalf of Safe 3. order may use off-chain ERC-1271 signature (Rabby can simulate Safe signing) or route through Safe TX — verify which path Rabby uses 4. TWAP availability depends on fallback handler | H9: Not Run | I9: Rabby's Safe import allows off-chain-style signing for Safe — behaviour may differ from native Safe App or WC connection. Verify fee logic: no Safe App fee; check whether gasless/bundling applies. Also, not TX bundling. Onchain TX resoinses are not detected: see https://github.com/cowprotocol/cowswap/issues/6755
A10: SW-06 | B10: Fee: Safe App License Fee (0.1%) applied inside Safe App | C10: High | D10: Functional | E10: CoW Swap open inside Safe App (SW-01 or SW-06 context) | F10: 1. Open CoW Swap inside Safe App (app.safe.global or mobile) 2. Select any non-correlated token pair 3. Enter a swap amount 4. Observe fee fields on the swap form and confirm modal | G10: 1. 'Safe App License Fee (0.1%)' label appears on swap form 2. shows estimated fee in tokens and USD 3. same label on Confirm modal 4. Receive (incl. costs) tooltip includes Safe App fee 5. fee NOT shown for correlated token pairs (e.g. USDC/DAI) | H10: Not Run | I10: Per spec: Safe charges 0.1% fee inside Safe App. Correlated pairs exempt correlated assets listed in https://cms.cow.fi/admin/content-manager/collection-types/api::correlated-token.correlated-token?page=1&pageSize=10&sort=name:ASC
A11: SW-07 | B11: Fee: Safe App License Fee NOT applied via WalletConnect | C11: High | D11: Functional | E11: Safe connected via WalletConnect (SW-03 or SW-04), NOT inside Safe App iframe | F11: 1. Connect Safe via WC to swap.cow.fi 2. Select same token pair as SW-07 3. Enter same amount 4. Compare fee fields | G11: 1. No 'Safe App License Fee' shown 2. only standard CoW Protocol network costs and any applicable volume fee 3. fee section shows standard breakdown | H11: Not Run | I11: Safe App fee = iframe context only, not WC context
A12: SW-08 | B12: Fee: SC wallet — no gasless transactions, '+gas' shown in Network costs | C12: High | D12: Functional | E12: Any Safe connection mode (SW-01 through SW-06) | F12: 1. Connect via any Safe method 2. Load a swap quote 3. Observe Network costs (est.) field 4. Check Receive (incl. costs) / From (incl. costs) tooltips | G12: 1. Network costs field shows '+gas' suffix 2. Fee field absent from Receive/From tooltips (when no other fee types present) 3. transactions are NOT gasless — SC wallets execute on-chain TXs | H12: Not Run | I12: Per spec: 'Transactions in SC wallets are not gasless ones. Fee field is absent from tooltips when no other fee types. Network costs shows +gas'
A13: SW-09 | B13: Fee: Safe App fee exempt for correlated token pairs | C13: Medium | D13: Functional | E13: CoW Swap inside Safe App; correlated token pair selected (e.g. USDC/DAI, USDC/USDT) | F13: 1. Open CoW Swap inside Safe App 2. Select a correlated token pair (stablecoin↔stablecoin) 3. Observe fee fields | G13: 1. Safe App License Fee NOT shown for correlated pairs 2. fee section shows 'Free' or standard network costs only | H13: Not Run | I13: Per spec: 'Fees not set to correlated token pairs' correlated assets listed in https://cms.cow.fi/admin/content-manager/collection-types/api::correlated-token.correlated-token?page=1&pageSize=10&sort=name:ASC
A14: SW-10 | B14: Bundling: Safe App — 'Approve + Swap' in single Safe TX | C14: High | D14: Functional | E14: CoW Swap inside Safe App; ERC-20 token with no prior approval | F14: 1. Select unapproved ERC-20 sell token inside Safe App 2. Observe action button area 3. Verify 'Token bundling' banner shown 4. Click 'Approve + Swap' 5. Check Safe TX queue | G14: 1. Both approval and swap bundled into single Safe TX 2. 'Approve + Swap' button shown 3. one TX in Safe queue (not two separate) 4. both signers approve once | H14: Not Run | I14: Safe App context supports bundling. Contrast with SW-13 for WC context
A15: SW-11 | B15: Bundling: WC-connected Safe — separate approval TX required | C15: High | D15: Functional | E15: Safe connected via WalletConnect; ERC-20 token with no prior approval | F15: 1. Connect Safe via WC 2. Select unapproved ERC-20 sell token 3. Observe action button — check if bundling banner appears 4. Complete approval flow | G15: 1. Both approval and swap bundled into single Safe TX 2. 'Approve + Swap' button shown 3. one TX in Safe queue (not two separate) 4. both signers approve once | H15: Not Run
A16: SW-12 | B16: Bundling: Rabby + Safe — verify whether bundling is supported | C16: Medium | D16: Functional | E16: Safe imported in Rabby; unapproved ERC-20 sell token | F16: 1. Connect via Rabby with imported Safe account 2. Select unapproved token 3. Observe action button and bundling banner presence | G16: 1. Bundling NOT available via WC connection 2. 'Allow CoW Swap to use your token' button shown (not Approve+Swap) 3. separate approval TX required before swap can proceed | H16: Not Run
A17: SW-13 | B17: TX deadline: Safe SC wallet max deadline = 720 min | C17: Medium | D17: Functional | E17: Safe wallet connected (any method); Settings open | F17: 1. Connect Safe wallet 2. Open Settings → TX deadline 3. Check maximum allowed deadline 4. Compare to EOA max (180 min) | G17: 1. Max deadline = 720 min for SC wallets vs 180 min for EOA 2. value above 720 rejected or clamped 3. default = 30 min unchanged | H17: Not Run
A18: SW-14 | B18: ETH-flow: bundling | C18: High | D18: Functional | E18: The app is opened inside Safe or connected to app using WC | F18: 1. Select ETH as sell token with Safe 2. Press on the "Wrap ETH and Swap button' | G18: Both wrapping, approval (if needed) and swap bundled into single Safe TX | H18: Not Run
A19: SW-15 | B19: ETH-flow: Safe uses wrap-WETH instead of native ETH-flow | C19: High | D19: Functional | E19: Safe wallet connected (any method); ETH in Safe | F19: 1. Select ETH as sell token with Safe connected via Rabby or connected to iOS safe app 2. Observe flow shown — should be wrap-WETH, not ETH-flow 3. Wrap ETH → WETH via Safe TX 4. Swap WETH as normal ERC-20 | G19: 1. ETH-flow NOT used for SC wallets 2. 'Wrap your ETH' section shown 3. wrapping creates Safe TX in queue 4. after WETH received, swap proceeds as ERC-20 order | H19: Not Run
A20: SW-16 | B20: TWAP: requires Safe with ExtensibleFallbackHandler not installed | C20: High | D20: Functional | E20: The app is opened inside Safe or connected to app using WC | F20: 1. Connect Safe without fallback handler | G20: Warning on the form is displayed to set up the FB handler A user needs to check the box before proceeding with an order Setting up the handler is included into the bundle along with TWAP order placement TX | H20: Not Run

Sheet SmartAccounts
A1: Smart Account Tests
A2: CoW Swap | swap.cow.fi | SmartAccounts
A4: ID | B4: Test Name | C4: Priority | D4: Type | E4: Preconditions | F4: Test Steps | G4: Expected Result | H4: Status | I4: Notes / Defect ID
A5: SA-01 | B5: MetaMask Smart Account: detected as EOA wallet in CoW Swap | C5: High | D5: Functional | E5: MetaMask extension with Smart Account (ERC-4337 based) enabled; account selected in MetaMask | F5: 1. Open MetaMask and switch to Smart Account 2. Connect to swap.cow.fi 3. Observe how CoW Swap classifies the wallet type | G5: 1. CoW Swap treats MetaMask Smart Account as a regular EOA wallet 2. no SC wallet UI shown 3. standard EOA swap flow available 4. ETH-flow (native ETH orders) accessible | H5: Not Run | I5: MM Smart Accounts are handled as regular EOA wallets — they appear as injected provider with EOA-like interface
A6: SA-02 | B6: MetaMask Smart Account: off-chain order signing works (EIP-712) | C6: High | D6: Functional | E6: MetaMask Smart Account connected | F6: 1. Connect MetaMask Smart Account 2. Place a market swap order 3. Observe signing prompt in MetaMask | G6: 1. EIP-712 typed data signing prompt shown (same as regular EOA) 2. no Safe-style TX queue 3. order submitted as off-chain intent 4. signs like EOA | H6: Not Run
A7: SA-03 | B7: MetaMask Smart Account: gasless permit available — same as EOA | C7: High | D7: Functional | E7: MetaMask Smart Account; permit-compatible ERC-20 sell token | F7: 1. Connect MetaMask Smart Account 2. Select permit-compatible sell token (e.g. USDC) 3. Observe approval flow — gasless permit option should be offered 4. Sign the permit message 5. Verify no on-chain approval TX is submitted | G7: 1. Gasless permit (EIP-2612) offered, same as regular EOA 2. off-chain permit signature works 3. no on-chain approval TX needed 4. same partial permit side-effect risk applies | H7: Not Run | I7: MM Smart Account treated as EOA for permit purposes. Warning about partial permit breaking other orders should appear in the same way as for EOA.
A8: SA-04 | B8: MetaMask Smart Account: ETH-flow accessible | C8: High | D8: Functional | E8: MetaMask Smart Account connected; ETH balance > 0 | F8: 1. Select ETH as sell token with MetaMask Smart Account 2. Observe flow — should be ETH-flow, not wrap-WETH | G8: 1. Native ETH-flow available (not wrap-WETH fallback) 2. UI does not show 'Wrap your ETH' section for SC wallet 3. order submitted on-chain as ETH-flow | H8: Not Run | I8: EOA treatment means ETH-flow is available, unlike Safe/Base SC wallets which must wrap first
A9: SA-05 | B9: MetaMask Smart Account: TWAP tab shows 'create Safe' prompt | C9: Medium | D9: Functional | E9: MetaMask Smart Account connected | F9: 1. Navigate to TWAP tab with MetaMask Smart Account | G9: TWAP form shows 'Unsupproted wallet' | H9: Not Run | I9: MM Smart Accounts do not satisfy TWAP's Safe requirement
A10: SA-06 | B10: MetaMask Smart Account: TX deadline max = 180 min (EOA limit) | C10: Medium | D10: Functional | E10: MetaMask Smart Account connected; Settings open | F10: 1. Open Settings → TX deadline 2. Check max value | G10: 1. Max TX deadline = 180 min (EOA limit, not 720 min SC limit) 2. consistent with EOA treatment | H10: Not Run
A11: SA-07 | B11: Base Smart Account: detected as SC wallet in CoW Swap | C11: High | D11: Functional | E11: Coinbase Wallet with Base Smart Account (ERC-4337) enabled; connected to swap.cow.fi | F11: 1. Connect Coinbase Wallet with Base Smart Account active 2. Observe how CoW Swap classifies the wallet | G11: 1. CoW Swap detects Base Smart Account as SC wallet 2. SC wallet UI behaviors applied: no ETH-flow, wrap-WETH required, no gasless permit, TX deadline max = 720 min, '+gas' in Network costs | H11: Not Run | I11: Base Smart Accounts act as SC wallets — same class as Safe but different provider
A12: SA-08 | B12: Base Smart Account: ETH requires wrap-WETH flow | C12: High | D12: Functional | E12: Base Smart Account connected; ETH balance > 0 | F12: 1. Select ETH as sell token 2. Observe UI | G12: 1. 'Wrap your ETH' section shown 2. native ETH-flow NOT available 3. must wrap ETH → WETH before swapping 4. same as Safe SC wallet ETH handling | H12: Not Run
A13: SA-09 | B13: Base Smart Account: gasless permit NOT available | C13: High | D13: Functional | E13: Base Smart Account connected; permit-compatible ERC-20 selected | F13: 1. Select a permit-compatible token (e.g. USDC) 2. Observe approval UI | G13: 1. No gasless permit option offered 2. standard on-chain approval TX required 3. no EIP-2612 permit signing prompt | H13: Not Run | I13: SC wallets cannot sign EIP-712 permits — applies to Base Smart Accounts too
A14: SA-10 | B14: Base Smart Account: bundling (Approve+Swap) supported | C14: High | D14: Functional | E14: Base Smart Account; unapproved ERC-20 sell token | F14: 1. Connect Base Smart Account 2. Select unapproved ERC-20 3. Observe action button | G14: User needs to approve a token first, then place an order | H14: Not Run
A15: SA-11 | B15: Base Smart Account: TX deadline max = 720 min (SC wallet limit) | C15: Medium | D15: Functional | E15: Base Smart Account connected; Settings open | F15: 1. Open Settings → TX deadline 2. Check max value | G15: 1. Max TX deadline = 720 min (SC wallet limit) 2. not limited to 180 min EOA limit | H15: Not Run
A16: SA-12 | B16: Base Smart Account: TWAP availability | C16: Medium | D16: Functional | E16: Base Smart Account connected | F16: 1. Navigate to TWAP tab 2. Check whether TWAP is available or what prompt is shown | G16: TWAP form shows 'Unsupproted wallet' | H16: Not Run | I16: Expected: TWAP not available for Base SA (Safe-specific feature); document actual prompt shown

Sheet MarketOrders
A1: Market Orders (Swap) Tests
A2: CoW Swap | swap.cow.fi | MarketOrders
A4: ID | B4: Test Name | C4: Priority | D4: Type | E4: Preconditions | F4: Test Steps | G4: Expected Result | H4: Status | I4: Notes / Defect ID
A5: MO-01 | B5: Sell order: ERC-20 → ETH | C5: High | D5: Functional | E5: EOA wallet connected; USDC balance > 0 | F5: 1. Select USDC as sell token, ETH as buy token 2. Enter sell amount 3. Approve if needed 4. Click Swap and sign | G5: 1. Order submitted off-chain 2. appears in open orders with status Open | H5: Not Run
A6: MO-02 | B6: Sell order: ERC-20 → ERC-20 | C6: High | D6: Functional | E6: EOA wallet; USDC balance > 0 | F6: 1. Select USDC → WETH 2. Enter amount 3. Approve token if needed 4. Swap and sign | G6: 1. Order submitted off-chain 2. appears in open orders with status Open | H6: Not Run
A7: MO-03 | B7: Buy order: specify exact buy amount (ERC-20) | C7: High | D7: Functional | E7: EOA wallet; sufficient sell token balance; buy order type selected in UI | F7: 2. Select USDC as sell token, WETH as buy token 3. Enter exact buy amount (e.g. 0.5 WETH) 4. Observe 'From (incl. costs)' sell amount calculated 5. Check Maximum sent amount (Receive incl. costs + Slippage) 6. Place order | G7: 1. Order submitted off-chain 2. appears in open orders with status Open | H7: Not Run
A8: MO-04 | B8: Buy order: approval amount includes slippage buffer | C8: High | D8: Functional | E8: token not yet approved | F8: 1. Specify a buy order for token X 2. Observe the approval prompt amount 3. Compare approval amount to 'From (incl. costs)' + slippage % | G8: Approval amount = Maximum sent amount = Receive (incl. costs) + slippage buffer+1% | H8: Not Run
A9: MO-05 | B9: Buy order: ETH as sell token (ETH-flow buy not supported) | C9: Medium | D9: Functional | E9: ETH-flow context (ETH as sell token, EOA wallet) | F9: 1. Select ETH as sell token 2. Attempt to switch to Buy order mode | G9: 1. Buy field is disabled for ETH-flow 2. only Sell order type available | H9: Not Run | I9: ETH-flow is sell-only per spec
A10: MO-06 | B10: Swap form: To field amount calculation | C10: High | D10: Functional | E10: Both tokens selected; sell amount entered | F10: 1. Enter sell amount (e.g. 100 USDC) 2. Observe To field 3. Verify: To amount = Sell amount × Price (from BE) 4. Verify USD estimation shown for both fields 5. Verify price impact shown near USD estimation with tooltip 'Price impact due to current liquidity levels' | G10: 1. To amount = Sell amount × Price (e.g. if price of 1 ETH = 16 GNO, selling 1 ETH shows 16 GNO) 2. USD estimations present 3. price impact % shown | H10: Not Run | I10: Per spec: 'Amount in the To field = Sell amount × Price'
A11: MO-07 | B11: Swap form: 'Receive (incl. costs)' field calculation | C11: High | D11: Functional | E11: Quote loaded with non-zero fee and network costs | F11: 1. Load a swap quote 2. Hover over 'Receive (incl. costs)' tooltip 3. Verify tooltip grid shows: Before costs, Network costs, Fee, TO value 4. Verify: Receive (incl. costs) = To amount − Network costs − Fee | G11: 1. Tooltip shows calculation breakdown 2. TO = Before costs − Network costs 3. Receive (incl. costs) matches formula 4. values consistent with Network costs (est.) field | H11: Not Run | I11: Per spec: 'Calculated as Receive amount − Network costs − fee'
A12: MO-08 | B12: Swap form: 'Minimum receive' calculation in Confirm modal | C12: High | D12: Functional | E12: Swap confirm modal open | F12: 1. Proceed to Confirm Swap modal 2. Note 'Expected to receive' value 3. Note slippage % in settings 4. Verify 'Minimum receive' = Expected to receive × (1 − slippage% / 100) | G12: 1. Minimum receive = Expected to receive × (1 − slippage/100) 2. field shown read-only 3. value updates when slippage changes | H12: Not Run | I12: Per spec: 'Minimum receive = Expected to receive × (1 − slippage%/100)'
A13: MO-09 | B13: Swap form: MAX button deducts 0.01 ETH for gas | C13: Medium | D13: Functional | E13: ETH selected as sell token; ETH balance > 0.01, user is connected to EOA wallet | F13: 1. Select ETH as sell token 2. Click MAX button 3. Observe the filled amount | G13: 1. Amount = ETH balance − 0.01 (to cover gas costs) 2. not the full balance | H13: Not Run | I13: This does not apply to smart-contract wallets: max button preseletcs 100% of a native token
A14: MO-10 | B14: Confirm modal: price update banner | C14: Medium | D14: Functional | E14: Confirm Swap modal open; quote refreshes while modal is open | F14: 1. Open Confirm Swap modal 2. Wait for price to update 3. Observe banner 4. Click Accept on the banner | G14: 1. 'Price updated' banner appears 2. Confirm Swap button disabled until Accept clicked 3. new price reflected after accepting | H14: Not Run
A15: MO-11 | B15: ETH-flow: place ETH sell order (EOA wallet) | C15: High | D15: Functional | E15: EOA wallet connected; ETH balance > 0; | F15: 1. Select ETH as sell token, any ERC-20 as buy token 2. Enter ETH amount 3. Review form: From field (ETH amount + USD), To field (buy amount + USD + price impact), Receive (incl. costs), Price, Fee, Network costs, Slippage, Expiration 4. Click Swap 5. Sign the ON-CHAIN transaction in wallet | G15: 1. ETH-flow order submitted on-chain (not off-chain intent) 2. status shows 'Creating' with TX creation hash 3. progresses to 'Open' once TX executes 4. ETH deducted from balance at Open state | H15: Not Run | I15: ETH-flow uses on-chain TX, not off-chain signature. SC wallets use classic wrap-WETH flow instead
A16: MO-12 | B16: ETH-flow: SC wallet falls back to wrap-WETH flow | C16: High | D16: Functional | E16: Smart contract wallet (Safe via Rabby or Base smart wallet) connected; ETH balance > 0 | F16: 1. Select ETH as sell token 2. Observe UI — 'Wrap your ETH' section should appear 3. Wrap ETH → WETH 4. Proceed with WETH swap as normal ERC-20 | G16: 1. SC wallet does not use ETH-flow 2. classic wrap-then-swap flow shown 3. no direct on-chain ETH order created | H16: Not Run
A17: MO-13 | B17: ETH-flow: SC wallet: Safe+bundling | C17: High | D17: Functional | E17: Safe viz WC or the app inside Safe connected; ETH balance > 0 | F17: 1. Select ETH as sell token, an amount to sell 2. Pick ERC 20 token to buy 3. verify the button | G17: 1. SC wallet does not use ETH-flow 2. classic: it bundles wrap+approveWETH(if needed) and a swap in 1 transaction. | H17: Not Run
A18: MO-14 | B18: ETH-flow: order status lifecycle | C18: High | D18: Functional | E18: ETH-flow order placed | F18: 1. Submit ETH-flow order → verify status = 'Creating'; TX hash shown 2. Wait for TX to execute → verify status = 'Open'; ETH deducted; Explorer link appears 3. Wait for fill → verify status = 'Filled'; buy token in wallet; 3rd stepper circle green; cancel no longer possible | G18: 1. Status transitions: Creating → Open → Filled 2. correct TX links at each step 3. ETH deducted at Open 4. buy token received at Filled | H18: Not Run
A19: MO-15 | B19: ETH-flow: order submission TX fails | C19: Medium | D19: Negative | E19: ETH-flow order submitted; TX fails on-chain | F19: 1. Submit ETH-flow order 2. Simulate or observe a TX failure (e.g. gas too low) 3. Check order status and balance | G19: 1. Status = 'Failed' 2. ETH NOT deducted (only TX costs) 3. stepper shown in red 4. cancel not possible 5. TX hash still linked | H19: Not Run
A20: MO-16 | B20: ETH-flow: cancel order (on-chain cancellation) | C20: Medium | D20: Functional | E20: ETH-flow order in 'Open' or 'Creating' state | F20: 1. Click cancel on open ETH-flow order 2. Confirm cancellation TX in wallet 3. Monitor status → 'Cancelling' 4. Wait for cancellation TX to mine → status 'Cancelled' | G20: 1. 'Cancelling' state: ETH still deducted, cancellation TX link shown under 3rd stepper step 2. 'Cancelled' state: ETH NOT returned (only TX costs taken) 3. 2nd step shown in red | H20: Not Run | I20: ETH cancellation is on-chain. Cancelled ETH is NOT refunded — only TX gas costs
A21: MO-17 | B21: ETH-flow: order expired — ETH refunded | C21: Medium | D21: Functional | E21: ETH-flow order in Open state; TX deadline reached without fill | F21: 1. Place ETH-flow order with short deadline 2. Let it expire without fill 3. Check status, balance, stepper | G21: 1. Status = 'Expired' 2. ETH refunded to user balance (only TX costs taken) 3. refund TX link shown under 3rd stepper step 4. stepper shown in green | H21: Not Run | I21: Contrast with 'Failed' where ETH not refunded. Note known bug: https://github.com/cowprotocol/cowswap/issues/4153
A22: MO-18 | B22: TX deadline: default value and limits (regular flow) | C22: High | D22: Functional | E22: EOA wallet connected; swap settings open | F22: 1. Open Settings 2. Check TX deadline default value 3. Try setting below minimum (< 2 min) 4. Try setting above maximum for EOA (> 180 min) 5. Reconnect with SC wallet and verify max changes to 720 min | G22: 1. Default = 30 min 2. min = 2 min (regular flow) 3. max EOA = 180 min 4. max SC wallet = 720 min 5. values outside range rejected or clamped | H22: Not Run | I22: Per spec. ETH-flow has different limits: min 10 min, max EOA 180 min, max SC 720 min
A23: MO-19 | B23: TX deadline: ETH-flow specific limits | C23: Medium | D23: Functional | E23: ETH-flow active (ETH sell token, EOA wallet); settings open | F23: 1. Open Settings with ETH-flow active 2. Check deadline default = 30 min 3. Try setting below 10 min 4. Try setting above 180 min (EOA) | G23: 1. ETH-flow min = 10 min (not 2 min) 2. deadline field labeled as 'modified' 3. values outside range rejected | H23: Not Run | I23: Per spec: ETH-flow min = 10 min vs regular flow min = 2 min
A24: MO-20 | B24: TX deadline: order expires after set deadline | C24: Medium | D24: Functional | E24: Order placed with short deadline (e.g. 2 min) | F24: 1. Set TX deadline to minimum (2 min) 2. Place order 3. Do not fill — wait for deadline to pass 4. Check order status | G24: Order status changes to 'Expired' after deadline; | H24: Not Run | I24: ~1 minute after real expiration
A25: MO-21 | B25: TX deadline: inactive tab quote expiry message | C25: Low | D25: Functional | E25: Quote loaded; tab left inactive for > 2 minutes | F25: 1. Load a swap quote 2. Leave the tab inactive for > 2 minutes 3. Return to tab | G25: 1. 'Quote expired. Refreshing…' message shown 2. refreshes within 10 seconds 3. if stuck > 10 sec may indicate BE rate limiting | H25: Not Run
A26: MO-22 | B26: Slippage: dynamic mode defaults and range (regular flow) | C26: High | D26: Functional | E26: Regular flow (ERC-20); settings open | F26: 1. Open Settings → Slippage 2. Verify dynamic is selected by default 3. Check dynamic range: min 0.5%, max dynamically up to 50% 4. Observe slippage auto-adjusts based on network conditions | G26: 1. Dynamic slippage selected by default 2. min = 0.5% 3. max = 50% 4. adjusts automatically 5. info banner 'Slippage adjusted to X% to ensure quick execution' appears when dynamic value > 2% | H26: Not Run
A27: MO-23 | B27: Slippage: manual mode — warnings at thresholds | C27: High | D27: Functional | E27: Regular flow; settings in manual slippage mode | F27: 1. Switch to manual slippage 2. Enter 0% → verify behavior 3. Enter 50% → verify accepted as max 4. Try entering 51% → verify rejected | G27: 1. 0.0% threshold: 'With low slippage, your transaction may expire. ' warning 2. >1% threshold: 'With high slippage, you may not get the best price.' warning 3. max = 50% 4. if dynamic disabled, 0.5% applied as default 5. 'recommended' label appears near value when dynamic is off | H27: Not Run | I27: Per spec: regular flow manual slippage
A28: MO-24 | B28: Slippage: ETH-flow defaults and limits | C28: Medium | D28: Functional | E28: ETH-flow active; settings open | F28: 1. Open Settings with ETH selected 4. Try setting below chain minimum 5. Try setting above 50% | G28: Min 0,5%, max 50% | H28: Not Run
A29: MO-25 | B29: Custom recipient: send swap output to different address | C29: High | D29: Functional | E29: Wallet connected; custom recipient field enabled in settings | F29: 1. Open Settings → enable Custom recipient 2. Enter a valid Ethereum address different from connected wallet 3. Place a swap order 4. On Confirm modal: verify warning about custom recipient is shown above Confirm button 5. Confirm and sign | G29: 1. Buy tokens received at the custom recipient address, not the connected wallet 2. warning displayed on confirm modal 3. order placed successfully | H29: Not Run
A30: MO-26 | B30: Custom recipient: field validation — invalid address | C30: High | D30: Negative | E30: Custom recipient field visible | F30: 1. Enter a non-address string (e.g. 'abc123') 2. Enter a partial address 3. Enter an address with wrong checksum 4. Observe field state | G30: 1. Recipient field value highlighted in red/error 2. 'Enter a valid recipient' error message displayed 3. Swap button disabled while invalid | H30: Not Run | I30: Per spec: 'The recipient field's value is highlighted; Enter a valid recipient is displayed'
A31: MO-27 | B31: Custom recipient: cross-chain prefix warning | C31: Medium | D31: Functional | E31: Connected to Ethereum Mainnet; custom recipient field open | F31: 1. Enter a recipient address with a different chain prefix (e.g. 'base:0x...' while connected to Ethereum) 2. Observe warning near the recipient field | G31: 1. Additional warning displayed near recipient field: recipient prefix differs from connected chain 2. does not block swap but warns user | H31: Not Run | I31: Per spec: 'E.g. you are connected to Ethereum, but insert a recipient address like base:address'
A32: MO-28 | B32: Custom recipient: ENS name resolution | C32: Low | D32: Functional | E32: Connected to Ethereum Mainnet (ENS supported); custom recipient enabled | F32: 1. Enter a valid ENS name (e.g. 'vitalik.eth') in recipient field 2. Observe resolution | G32: 1. ENS name resolved to 0x address 2. resolved address shown 3. no error state only on Ethreum and sepolia | H32: Not Run
A33: MO-29 | B33: Insufficient balance: error on swap form and unfillable label in Account modal | C33: High | D33: Negative | E33: Wallet connected with known token balances | F33: 1. Select a sell token 2. Enter amount greater than wallet balance 3. Observe UI | G33: 1. 'Insufficient [Token] balance' error displayed on swap form 2. Swap button disabled 3. if an open order exists for the same token and balance drops below order amount, the order is labeled unfillable in the Account modal order list | H33: Not Run
A34: MO-30 | B34: Token not approved (non-permittable, no bundling): approval button shown, order unfillable in Account modal | C34: High | D34: Functional | E34: ERC-20 sell token with no existing approval; wallet does not support bundling | F34: 1. Select an ERC-20 sell token with zero approval 2. Enter swap amount 3. Observe action button state | G34: 1. 'Allow CoW Swap to use your token' button shown on swap form 2. Swap button disabled until approved 3. any open order for this token shown as unfillable in Account modal due to insufficient allowance 4. for buy orders approval amount = Receive (incl. costs) + slippage | H34: Not Run | I34: Per spec
A35: MO-31 | B35: Token not approved — bundling supported: Approve+Swap button shown | C35: High | D35: Functional | E35: ERC-20 sell token with no approval; wallet supports bundling (e.g. Safe ) | F35: 1. Select unapproved ERC-20 token 2. Observe UI — 'Token bundling' banner should appear 3. Verify 'Approve + Swap' button shown | G35: 1. 'Approve + Swap' button displayed 2. token bundling banner shown above action button 3. both approval and swap sent to wallet in one go 4. open orders for this token shown as unfillable in Account modal until approval completes | H35: Not Run
A36: MO-32 | B36: Fee ≥ 30% of sell amount: red banner with 'Swap anyways' checkbox | C36: High | D36: Negative | E36: Trade with very small sell amount relative to network costs | F36: 1. Enter a very small sell amount so network fees ≥ 30% of sell value 2. Observe banner and button state | G36: 1. Red banner displayed 2. 'Swap anyways' checkbox shown unchecked 3. Swap button disabled until checkbox checked 4. red read-only banner also shown on Confirm modal | H36: Not Run | I36: Per spec: fee thresholds 30%=red, 20%=orange, 10%=yellow
A37: MO-33 | B37: Fee ≥ 20% orange banner, fee ≥ 10% yellow banner | C37: Medium | D37: Negative | E37: Trade amounts triggering fee thresholds | F37: 1. Enter amount where fee is 20–29% of sell value → observe orange banner 2. Enter amount where fee is 10–19% → observe yellow banner 3. In both cases verify 'Swap anyways' checkbox and button behavior | G37: 1. Orange banner at ≥20% 2. yellow banner at ≥10% 3. each requires user to check 'Swap anyways' box to enable Swap button 4. corresponding read-only banner shown on Confirm modal | H37: Not Run | I37: Per spec
A38: MO-34 | B38: Sell amount too small to cover min fee: error shown | C38: Medium | D38: Negative | E38: Very small sell amount entered | F38: 1. Enter a tiny sell amount (e.g. 0.0001 USDC) 2. Observe error | G38: 1. Error message displayed: sell amount not enough to cover minimum fee 2. Network costs (est.) field shown above the error with min trade amount | H38: Not Run | I38: Per spec: 'Error is displayed when sell amount is not enough to cover a min fee'
A39: MO-35 | B39: TWAP suggestion banner for large high-impact orders | C39: Medium | D39: Functional | E39: User has balance; large order (>$50k Mainnet / >$500 other chains); price impact > 1% | F39: 1. On Mainnet: enter sell amount > $50,000 USD equivalent 2. Ensure price impact > 1% 3. Observe banner | G39: 1. 'Minimize price impact with TWAP' banner displayed 2. thresholds: Mainnet $50k, Gnosis/Arbitrum/Base $500, Sepolia $100 | H39: Not Run | I39: Per spec thresholds
A40: MO-36 | B40: Error: no liquidity / token not supported | C40: Medium | D40: Negative | E40: Token pair with no liquidity or unsupported token selected | F40: 1. Select an obscure or unsupported token as sell or buy 2. Enter any amount | G40: 1. 'Insufficient liquidity for this trade' error message displayed 2. Swap button disabled | H40: Not Run | I40: Same message for both 'token not supported' and 'no liquidity for pair' cases
A41: MO-37 | B41: Error: price impact ≥ 5% — confirm price modal | C41: High | D41: Functional | E41: Trade with price impact ≥ 5% but < 10% | F41: 1. Set up trade with ≥5% price impact 2. Click 'Confirm Swap' 3. Observe additional confirmation modal | G41: 1. Secondary 'Confirm price' modal appears after clicking Confirm Swap 2. wallet signing request only sent after user confirms this modal | H41: Not Run | I41: Per spec
A42: MO-38 | B42: Error: price impact > 10% — type 'Confirm' to proceed | C42: High | D42: Functional | E42: Trade with price impact > 10% | F42: 1. Set up trade with >10% price impact 2. Click 'Confirm Swap' 3. In the additional modal, type 'Confirm' in the text field 4. Proceed | G42: 1. Confirm price modal requires user to manually type 'Confirm' before proceeding 2. adds friction for high-impact trades | H42: Not Run | I42: Per spec
A43: MO-39 | B43: Error: impossible to calculate price impact | C43: Medium | D43: Negative | E43: Token pair where inverse price cannot be fetched | F43: 1. Select a token pair where price impact cannot be computed 2. Observe banner | G43: 1. Yellow warning message displayed 2. 'Swap anyway' checkbox shown unchecked 3. Swap disabled until checkbox checked 4. read-only banner on Confirm modal | H43: Not Run | I43: Per spec
A44: MO-40 | B44: Error: offline state | C44: Medium | D44: Negative | E44: Browser taken offline after app loaded | F44: 1. Load swap.cow.fi normally 2. Disable network connection 3. Attempt to fetch a quote | G44: 'Error loading price. You're currently offline' message displayed | H44: Not Run | I44: Per spec
A45: MO-41 | B45: Error: unsupported network | C45: Medium | D45: Negative | E45: Wallet connected to unsupported chain (e.g. custom testnet) | F45: 1. Switch wallet to unsupported network 2. Observe swap form | G45: 1. Form fields empty and disabled 2. 'Unsupported network' message displayed | H45: Not Run | I45: Per spec
A46: MO-42 | B46: Token approval: first-time ERC-20 approval | C46: High | D46: Functional | E46: No prior approval for sell token; wallet does not support bundling | F46: 1. Select ERC-20 sell token with no approval 2. Enter amount 3. Click 'Allow CoW Swap to use your token' 4. Confirm approval TX in wallet | G46: 1. Approval TX executed on-chain 2. Swap button becomes enabled | H46: Not Run
A47: MO-43 | B47: Token approval: gasless approval (EIP-2612 permit) | C47: High | D47: Functional | E47: Sell token supports EIP-2612 permit (e.g. USDC, DAI on supported chains) | F47: 1. Select permit-compatible sell token 2. Sign off-chain permit message (no gas) | G47: 1. No approval TX mined 2. approval signed and is executed with first swap settlement 3. no gas charged for approval step | H47: Not Run
A48: MO-44 | B48: Quote expiry: auto-refresh and countdown timer | C48: Medium | D48: Functional | E48: Quote displayed in swap form | F48: 1. Load a quote 2. Observe countdown timer 3. Let timer reach zero | G48: 1. Countdown timer visible 2. quote refreshes automatically 3. brief loading state 4. new quote shown without user action | H48: Not Run
A49: MO-45 | B49: Order history: completed swap details correct | C49: Medium | D49: Functional | E49: At least one completed swap | F49: 1. Navigate to order history / activity 2. Find the completed order 3. Verify all fields | G49: Order shows: token pair, sell amount, received amount, execution price, status (Filled), TX link to correct block explorer for current network | H49: Not Run
A50: MO-46 | B50: Not connected state: Connect Wallet button shown | C50: Medium | D50: Functional | E50: No wallet connected | F50: 1. Open swap.cow.fi without connecting wallet 2. Attempt to interact with swap form | G50: 1. 'Connect Wallet' button displayed instead of Swap action button 2. if an error state also present, error shown instead of Connect Wallet button | H50: Not Run | I50: Per spec
A51: MO-47 | B51: Wrap ETH → WETH via swap form | C51: High | D51: Functional | E51: EOA or SC wallet connected on Ethereum; ETH balance > 0 | F51: 1. Select ETH as sell token, WETH as buy token 2. Enter amount to wrap 3. Observe action button — should show 'Wrap' not 'Swap' 4. Click Wrap 5. Confirm on-chain transaction in wallet | G51: 1. On-chain Wrap TX submitted 2. WETH balance increases by wrapped amount 3. ETH balance decreases by same amount 4. no off-chain order created 5. no fee charged beyond gas | H51: Not Run | I51: Wrap is a special 1:1 on-chain operation, not a CoW Protocol order
A52: MO-48 | B52: Unwrap WETH → ETH via swap form | C52: High | D52: Functional | E52: Wallet connected; WETH balance > 0 | F52: 1. Select WETH as sell token, ETH as buy token 2. Enter amount to unwrap 3. Observe action button — should show 'Unwrap' 4. Click Unwrap 5. Confirm on-chain transaction in wallet | G52: 1. On-chain Unwrap TX submitted 2. ETH balance increases by unwrapped amount 3. WETH balance decreases 4. 1:1 exchange rate, no slippage or protocol fee | H52: Not Run
A53: MO-49 | B53: Wrap ETH → WETH: 1:1 rate, no price impact shown | C53: Medium | D53: Functional | E53: ETH → WETH pair selected | F53: 1. Select ETH → WETH 2. Enter any amount 3. Observe price/fee/impact fields | G53: 1.token amounts are 1:1 2. no price impact displayed 3. fee shown as zero or hidden 4. Receive (incl. costs) = sell amount exactly | H53: Not Run
A54: MO-50 | B54: Wrap: SC wallet flow (wrap inside Safe) | C54: Medium | D54: Functional | E54: Safe wallet connected; ETH balance in Safe > 0 | F54: 1. Select ETH → WETH inside CoW Swap (Safe App) 2. Click Wrap 3. Observe Safe TX queue | G54: 1. Wrap transaction appears in Safe TX queue 2. requires threshold signatures 3. executes as on-chain WETH deposit | H54: Not Run | I54: SC wallets need on-chain TX for wrap, same as ETH-flow
A55: MO-51 | B55: Buy order: 'From (incl. costs)' tooltip breakdown | C55: Medium | D55: Functional | E55: Buy order mode; quote loaded | F55: 1. Place a buy order 2. Hover over 'From (incl. costs)' field 3. Inspect tooltip grid | G55: 1. Tooltip shows: Before costs, Network costs, Fee, maximum From amount 2. values consistent with displayed fields | H55: Not Run | I55: Mirror of 'Receive (incl. costs)' tooltip for sell orders
A56: MO-52 | B56: Sell vs Buy order: switching mode recalculates amounts | C56: Medium | D56: Functional | E56: Both tokens selected; amount entered | F56: 1. Enter amount in Sell mode 2. Switch to Buy mode 3. Enter same numeric value in Buy field 4. Compare resulting opposite-side amounts | G56: 1. Switching order type re-fetches quote 2. no stale quote used | H56: Not Run
A57: MO-53 | B57: Approval: full approval — unlimited allowance | C57: High | D57: Functional | E57: ERC-20 sell token; no prior approval; wallet does not prompt for custom amount | F57: 1. Select ERC-20 sell token with no approval Select a full approval amount option 2. Click 'Allow CoW Swap to use your token' 3. Observe the approval amount in wallet confirmation 4. Confirm TX | G57: 1. Full (unlimited / max uint256) approval granted by default 2. single approval TX covers all future trades of this token 3. spender = CoW Protocol contract address | H57: Not Run
A58: MO-54 | B58: Approval: partial approval — exact trade amount only | C58: High | D58: Functional | E58: ERC-20 sell token; wallet or UI supports partial/exact approval amount | F58: 1. Enable Partial approvals option in the settings (if not yet enabled) 2. select partial approval option after getting a quote 4. Confirm partial approval TX 5. Attempt another trade requiring more allowance | G58: 1. Partial approval accepted 2. first trade executes within approved amount 3. second trade triggers new approval prompt because allowance insufficient 4. no silent failure — clear 'insufficient allowance' UI shown | H58: Not Run
A59: MO-55 | B59: Approval: gasless permit — SC wallet falls back to on-chain approval | C59: High | D59: Functional | E59: Safe or other SC wallet connected; permit-compatible ERC-20 token selected | F59: 1. Connect Safe wallet 2. Select permit-compatible ERC-20 (e.g. USDC) 3. Observe approval UI — gasless should NOT be offered (SC wallet cannot sign permits) 4. Verify on-chain approval flow shown instead | G59: 1. No gasless/permit option shown for SC wallet 2. standard on-chain approval TX required 3. Safe TX created in queue for approval 4. no 'sign permit' prompt shown | H59: Not Run | I59: EIP-2612 permit requires EOA private key signing — SC wallets cannot do this
A60: MO-56 | B60: Approval: allowance check before each swap | C60: Medium | D60: Functional | E60: Previously approved token; allowance partially consumed | F60: 1. Previously gave partial approval for token X (e.g. 100 USDC) 2. Open CoW Swap with token X as sell token 3. Enter amount less than remaining allowance 4. Enter amount greater than remaining allowance | G60: 1. For amount ≤ remaining allowance: no approval prompt 2. swap proceeds directly 3. for amount > allowance: approval prompt shown with correct shortfall 4. current allowance displayed if possible | H60: Not Run
A61: MO-57 | B61: Cancel market order: off-chain soft cancellation (EOA) | C61: High | D61: Functional | E61: EOA wallet; active market order with status 'Open' (not yet filled) | F61: 1. Find open market order in orders table 2. Click ⋮ menu → Cancel 3. Sign off-chain cancellation message in wallet (no gas) | G61: 1. Cancellation message signed off-chain 2. no gas TX 3. order status changes to 'Cancelling' then 'Cancelled' 4. solvers stop filling the order 5. no fee charged for cancellation | H61: Not Run | I61: Market orders are off-chain intents — cancellation is also off-chain for EOA. Race condition possible if fill happens simultaneously
A62: MO-58 | B62: Cancel market order: race condition — order filled before cancel | C62: Medium | D62: Negative | E62: EOA wallet; open market order near its execution price | F62: 1. Place market order at current market price 2. Immediately attempt to cancel 3. Observe outcome — may be filled or cancelled | G62: 1. If order fills before cancellation is processed: status shows 'Filled' not 'Cancelled' 2. UI reflects actual outcome 3. no double-execution 4. clear status message explaining what happened | H62: Not Run | I62: Soft cancellation is best-effort — solvers may fill the order in the same batch before cancel is received
A63: MO-59 | B63: Cancel market order: SC wallet — on-chain TX cancellation | C63: High | D63: Functional | E63: Safe or SC wallet; active market order | F63: 1. Open orders table with Safe connected 2. Click cancel on open market order 3. Observe: Safe TX created in queue 4. Collect signatures and execute cancellation TX | G63: 1. On-chain cancellation TX in Safe queue 2. requires threshold signatures 3. order cancelled on-chain with finality 4. gas paid for cancellation TX | H63: Not Run | I63: SC wallets always cancel on-chain
A64: MO-60 | B64: Gasless permit: UI warning — partial permit may make other open orders unfillable | C64: High | D64: Functional | E64: EOA or MM Smart Account; permit-compatible sell token; at least one other open swap or limit order already exists for the same sell token | F64: 1. Have an existing open swap or limit order for token X (signed with permit or on-chain approval) 2. Place a new swap or limit order for the same token X 3. When gasless permit approval is offered, observe the UI before signing 4. Check whether a warning is shown about potential impact on other open orders | G64: 1. Warning section visible in the approval UI: gasless partial permit may reduce the effective allowance available to other open orders 2. warning explains that existing open orders using the same token may become unfillable if permit amount is less than their combined required amount 3. user can acknowledge and proceed or switch to on-chain approval instead | H64: Not Run
A65: MO-61 | B65: Gasless partial permit: existing open swap order becomes unfillable | C65: High | D65: Functional | E65: EOA wallet; open market swap order for token X using permit-based allowance; new swap order placed for same token X with a partial permit amount smaller than what the existing order needs | F65: 1. Place swap order A for 100 USDC using gasless permit (permit for 100 USDC signed) 2. Place swap order B for 70 USDC — sign a new gasless permit for exactly 50 USDC 3. wait till one of orders is executed | G65: Another order becomes labeled as unfillable (insufficient allowance); | H65: Not Run | I65: The new partial permit effectively replaces the previous allowance for the solver. Order A was relying on the old permit; the new smaller permit breaks it.
A66: MO-62 | B66: Gasless partial permit: existing open limit order becomes unfillable | C66: High | D66: Functional | E66: EOA wallet; open limit order for token X; new swap or limit order placed for same token X with partial gasless permit | F66: 1. Place limit order for 200 USDC (permit signed for 200 USDC) 2. Place a new market swap for 50 USDC — sign gasless permit for 50 USDC only 3. Observe limit order status in orders table | G66: 1. Limit order labeled unfillable due to insufficient allowance from the new partial permit 2. unfillable indicator shown 3. limit order not cancelled 4. limit order becomes fillable again once allowance is restored via on-chain approval | H66: Not Run
A67: MO-63 | B67: Unfillable permit order: only on-chain approval restores fillability | C67: High | D67: Functional | E67: Order (swap or limit) in unfillable state due to insufficient permit allowance (broken by a subsequent partial permit) | F67: 1. Start with order in unfillable state from MO-70 or MO-71 2. Attempt to fix by signing another gasless permit for the required amount 3. Observe whether order becomes fillable 4. Now use on-chain approval instead: click 'Allow CoW Swap to use your token' and confirm TX 5. Observe order status after on-chain approval TX is confirmed | G67: 1. THERE IS ONLY ONe option to unblock the order: on-chain approval TX . after on-chain approval TX confirms, unfillable order becomes fillable again 2. unfillable indicator cleared 3. order eligible for execution at next batch | H67: Not Run | I67: On-chain approval sets ERC-20 allowance directly in contract state — not dependent on permit nonces or solver interpretation. This is the reliable path to unfreeze a permit-broken order.
A68: MO-64 | B68: Permit availability: not offered for Safe, Base Smart Account, or SC wallets | C68: High | D68: Functional | E68: SC wallet connected (Safe via any method, or Base Smart Account); permit-compatible ERC-20 selected | F68: 1. Connect Safe wallet (App, WC desktop, WC mobile, or Rabby+Safe) 2. Select permit-compatible ERC-20 sell token (e.g. USDC) 3. Observe approval options shown 4. Repeat with Base Smart Account connected | G68: 1. Gasless permit option NOT offered for any SC wallet connection 2. only on-chain approval available 3. no EIP-712 permit signing prompt 4. applies to: Safe App, Safe via WC desktop, Safe via WC mobile, Safe in Rabby, Base Smart Account 5. does NOT apply to: EOA wallets, MetaMask Smart Account (those get permit option) | H68: Not Run | I68: Permit matrix: EOA ✓ MM Smart Account ✓ Safe (all modes) ✗ Base SA ✗
A69: MO-65 | B69: Permit availability: offered for EOA and MetaMask Smart Account | C69: High | D69: Functional | E69: EOA wallet (MetaMask, Rabby EOA, etc.) or MetaMask Smart Account; permit-compatible ERC-20 | F69: 1. Connect standard EOA wallet 2. Select permit-compatible ERC-20 3. Verify gasless permit option shown 4. Disconnect; connect MetaMask Smart Account 5. Same token — verify gasless permit also offered | G69: 1. Gasless permit option offered for both standard EOA and MetaMask Smart Account 2. both can sign EIP-712 permit messages 3. permit flow completes without gas TX for both wallet types | H69: Not Run | I69: MetaMask Smart Account is treated as EOA by CoW Swap for permit purposes
A70: MO-66 | B70: Progress bar: regular order happy path — steps 1 → 2 → 3 → 4 | C70: High | D70: Functional | E70: EOA wallet; valid market swap order ready to place | F70: 1. Place a regular market swap order 2. Observe progress bar immediately after signing → Step 1 (Submitted) 3. Observe bar after order enters OPEN/ACTIVE state → Step 2 (Batching/Searching) 4. Observe bar when order reaches EXECUTING → Step 3 (Executing) 5. Observe bar when order is TRADED → Step 4 (Executed) | G70: 1. Bar advances in order: Step 1 → 2 → 3 → 4 2. no step is skipped 3. no step is repeated 4. Step 4 shows filled confirmation with received amounts | H70: Not Run | I70: Progress bar steps: Step 1 = Initiated/Submitted; Step 2 = Batching/Searching (OPEN/ACTIVE); Step 3 = Executing (EXECUTING); Step 4 = Executed/Filled (TRADED). Bar must never move backward past the earliest step it has already reached, except for the defined retry step-back from Step 3 → Step 2.
A71: MO-67 | B71: Progress bar: bar never regresses to Step 1 once past it | C71: High | D71: Functional | E71: Order placed; progress bar has advanced to Step 2 or beyond | F71: 1. Place order; confirm bar reaches Step 2 2. Simulate or observe an OPEN status returned from backend while bar is at Step 2+ 3. Observe whether bar moves back to Step 1 | G71: 1. Bar does NOT go back to Step 1 once it has left the initial state 2. OPEN status received after Step 2 keeps bar at Step 2 (still searching) 3. regression to Step 1 is a bug | H71: Not Run
A72: MO-68 | B72: Progress bar: fast fill still shows Executing (Step 3) before Executed (Step 4) | C72: High | D72: Functional | E72: Order expected to fill very quickly (e.g. liquid pair, small amount) | F72: 1. Place order that fills immediately 2. Watch progress bar closely — look for Step 3 (Executing) | G72: 1. Even on very fast fills, bar shows Step 3 (Executing) briefly before Step 4 (Executed) 2. bar does NOT jump directly from Step 1 or Step 2 straight to Step 4 3. Step 3 is always shown, even if only momentarily | H72: Not Run
A73: MO-69 | B73: Progress bar: ETH-flow order — full lifecycle, no regression to Step 1 | C73: High | D73: Functional | E73: EOA wallet; ETH-flow order (native ETH sell) | F73: 1. Place ETH-flow order (on-chain TX) 2. Observe bar at Step 1 (TX submitted) 3. Observe bar at Step 2 once TX executes and order is OPEN 4. Observe Step 3 (Executing) and Step 4 (Executed) 5. Verify bar never regresses to Step 1 after Step 2 reached | G73: 1. ETH-flow bar follows same Step 1→2→3→4 sequence 2. bar does NOT return to Step 1 after advancing 3. TX hash shown under Step 1 throughout | H73: Not Run
A74: MO-70 | B74: Progress bar: temporary allowance/balance lag does not show 'Price change' / unfillable screen | C74: High | D74: Functional | E74: Order placed; temporary approval/permit/bundled Safe approval lag occurs at the start | F74: 1. Place order requiring approval (gasless permit or bundled Safe approval) 2. After approval/permit flow completes, observe progress bar 3. Check if 'Price change' or unfillable screen appears briefly | G74: 1. Bar stays on normal batching/searching step (Step 2) after approval flow 2. temporary allowance or balance lag does NOT trigger the 'Price change' / unfillable screen 3. 'Price change' screen only appears for true price-derived unfillable cases (not lag) | H74: Not Run
A75: MO-71 | B75: Progress bar: true price-change unfillable — 'Price change' screen shown correctly | C75: High | D75: Functional | E75: Order placed; market price moves significantly away from order quote before fill | F75: 1. Place order 2. Market price moves significantly (order becomes genuinely unfillable due to price) 3. Observe progress bar state | G75: 1. 'Price change' / unfillable screen shown in the progress bar for genuine price-derived unfillable 2. distinct from allowance/balance lag — this screen is only for true price change cases 3. user can take action (cancel or wait for price to return) | H75: Not Run
A76: MO-72 | B76: Progress bar: stale delayed completion timer does not overwrite newer order state | C76: Medium | D76: Functional | E76: Order completes during a delayed completion timer window | F76: 1. Place order; observe delayed completion staging 2. Before the delayed timer fires, cancel the order or order state changes 3. Observe: does the old delayed timer resurrect the stale state? | G76: 1. Delayed completion timer does NOT overwrite newer order state (e.g. cancelled) 2. if order disappears from tracked state, timer does not recreate it 3. stale retained state self-prunes after grace period without requiring a rerender | H76: Not Run
A77: MO-73 | B77: Progress bar: bridge order — bridge step persists during reconnect/reload | C77: High | D77: Functional | E77: Cross-chain order in bridge step (after swap phase complete); page reloaded or wallet reconnected | F77: 1. Place cross-chain order; let swap phase complete → bar enters bridge step 2. Reload page or briefly disconnect/reconnect wallet 3. Observe progress bar after reconnect | G77: 1. Bridge progress step preserved during reload/reconnect 2. bar does NOT move backward to Executing (Step 3) when bridge context briefly disappears 3. when bridge context returns, bar continues from correct bridge step | H77: Not Run
A78: MO-74 | B78: Swap form: balances and USD estimations correct for tokens with different decimal precision | C78: High | D78: Functional | E78: Wallet connected on Ethereum Mainnet or Gnosis Chain; balances available in tokens with varying decimals: e.g. ETH (18), USDC (6), WBTC (8) | F78: 1. Select ETH (18 dec) as sell token → enter amount → verify From USD estimation 2. Select USDC (6 dec) as buy token → verify To amount and USD estimation 3. Hover 'Receive (incl. costs)' tooltip → verify cost breakdown values consistent 4. Switch pair to WBTC (8 dec) sell → USDC (6 dec) buy → repeat checks 5. Verify wallet balance shown for each token matches on-chain balance at correct precision | G78: 1. All USD estimations correct regardless of token decimal combination 2. wallet balance displayed with appropriate decimal places for each token 3. To amount = Sell amount × Price, correctly scaled across decimal mismatch 4. Receive (incl. costs) tooltip values consistent with form fields 5. no truncation, rounding errors, or off-by-decimal-place amounts | H78: Not Run | I78: Common precision combinations to cover: 18-decimal (ETH, WETH, DAI, COW) × 6-decimal (USDC, USDT) × 8-decimal (WBTC) × 0-decimal (MPS on Gnosis Chain). MPS (MetaPool Staking token) has 0 decimals — the smallest tradeable unit IS 1 whole token; no fractional amounts possible. USD estimations must use correct decimal scaling for each token.
A79: MO-75 | B79: Swap form: 0-decimal token (MPS on Gnosis Chain) — balance, amounts, USD estimation | C79: High | D79: Functional | E79: Wallet connected on Gnosis Chain; MPS (0-decimal ERC-20) balance available in wallet | F79: 1. Switch to Gnosis Chain 2. Select MPS as sell token 3. Observe balance display — should show whole integer, no decimal places 4. Enter sell amount (e.g. 1, 10, 100 MPS) 5. Attempt to enter fractional amount (e.g. 0.5 MPS) 6. Observe USD estimation for the sell amount 7. Select any buy token and verify buy amount calculated correctly 8. Select MPS as buy token in a different pair; verify buy amount shown as integer | G79: 1. MPS balance shown as whole integer (no .000... suffix) 2. fractional input (0.5 MPS) rejected or rounded to nearest whole number with clear indication 3. USD estimation = integer amount × MPS price, no decimal shift errors 4. buy amount for MPS shown as integer 5. price field shows correct rate without decimal scaling artifacts | H79: Not Run | I79: MPS is a 0-decimal ERC-20 on Gnosis Chain. The UI must not allow fractional input (e.g. 0.5 MPS) and must display balance and amounts as whole integers. USD estimation must multiply by token price without decimal shifting errors.
A80: MO-76 | B80: USDT approval: revoke-then-approve flow for market swap when existing allowance < order amount (Ethereum) | C80: High | D80: Functional | E80: EOA wallet on Ethereum Mainnet; existing USDT allowance for CoW Protocol is non-zero but less than the order amount (e.g. 2 USDT approved, ordering 4 USDT) | F80: 1. Connect EOA wallet on Ethereum Mainnet 2. Navigate to the Swap tab 3. Select USDT as sell token (verify existing allowance is 2 USDT) 4. Enter a sell amount that exceeds the existing allowance (e.g. 4 USDT) 5. Observe the approval UI — should show a 2-step approval flow, not a single approve 6. Click the approval action 7. Sign the first transaction (approve(0) to revoke existing allowance) 8. Wait for the revoke TX to confirm on-chain 9. Sign the second transaction (approve(amount) for the new amount) 10. Wait for the approve TX to confirm 11. Place the market swap as normal | G80: 1. UI displays a 2-step approval flow specific to USDT (revoke first, then approve) 2. First TX is approve(0) sent to USDT contract — sets allowance to 0 3. Revoke TX confirms successfully on-chain 4. Second TX is approve(newAmount) — sets allowance to the required amount 5. Approve TX confirms successfully (does not fail like a single-step approve would) 6. Market swap can be placed and submitted normally after both TXs confirm 7. No 'approval failed' error encountered 8. Verify on revoke.cash that the final allowance equals the requested amount | H80: Not Run
A81: MO-77 | B81: USDT approval: no revoke or approve needed for market swap when existing allowance ≥ order amount | C81: Medium | D81: Functional | E81: existing USDT allowance for CoW Protocol is zero or more than an order amount | F81: 1. Connect EOA wallet on Ethereum Mainnet 2. Navigate to the Swap tab 3. Select USDT as sell token (verify existing allowance is e.g. 100 USDT) 4. Enter a sell amount ≤ existing allowance (e.g. 4 USDT) 5. Observe approval UI 6. Proceed with the market swap | G81: 1. No approval prompt shown — existing allowance is sufficient 2. No revoke TX requested 3. No approve TX requested 4. Market swap proceeds directly to signing/placement 5. USDT allowance is not modified | H81: Not Run | I81: Verifies the 2-TX flow is correctly skipped when not needed. USDT-specific behavior should not impose unnecessary transactions.
A82: MO-78 | B82: Swap form: protocol fee applied at 0.02% (2 bps) for standard token pair | C82: High | D82: Functional | E82: Wallet connected; standard non-correlated pair selected (e.g. WETH → USDC); sell amount entered | F82: 1. Load a swap quote for a standard pair (WETH → USDC) 2. Hover 'Receive (incl. costs)' tooltip 3. Read the 'Protocol fee' line in the breakdown 4. Compute Protocol fee / Before costs | G82: 1. Tooltip shows 'Protocol fee' row with a non-zero negative amount in the surplus (buy) token 2. Protocol fee ≈ Before costs × 0.0002 (2 bps) 3. 'To' = Before costs − Protocol fee − Network costs | H82: Not Run | I82: Per docs (Volume Fee, Standard Assets): Volume × 0.0002 = 0.02%. Fee charged in surplus token (buy token for sell orders). Validate against displayed 'Protocol fee' in the costs tooltip.
A83: MO-79 | B83: Swap form: protocol fee applied at 0.003% (0.3 bps) for correlated assets (stables/RWAs) | C83: High | D83: Functional | E83: Wallet connected; correlated pair selected (e.g. USDC → USDT or DAI → USDC); sell amount entered | F83: 1. Load a swap quote for a correlated pair (USDC → USDT) 2. Hover 'Receive (incl. costs)' tooltip 3. Read the 'Protocol fee' line 4. Compute Protocol fee / Before costs 5. Repeat with another stable/RWA correlated pair (e.g. DAI → USDC) | G83: 1. Tooltip shows 'Protocol fee' row with a non-zero negative amount in the surplus token 2. Protocol fee ≈ Before costs × 0.00003 (0.3 bps) 3. Fee is ~6.67× smaller than the standard 0.02% tier on equivalent volume | H83: Not Run | I83: Per docs (Volume Fee, Correlated Assets — Stables/RWAs): Volume × 0.00003 = 0.003%. Pairs include stablecoin↔stablecoin and RWA pairs as classified by CoW Protocol.

Sheet LimitOrders
A1: A4:F50
A2: B5
A3: B5:F15
A4: ID | B4: Test Name | C4: Priority | D4: Type | E4: Preconditions | F4: Test Steps | G4: Expected Result | H4: Status | I4: Notes / Defect ID
A5: LO-01 | B5: Place buy limit order | C5: High | D5: Functional | E5: Wallet connected; sufficient sell token balance | F5: 1. Click 'Limit' tab 2. Set sell token, buy token 3. Enter an exact amount into the Buy token field 4. set a limit price 5. Click 'Place limit order' 6. Sign in wallet | G5: 1. Limit order created 2. visible in open orders panel. Order type ia s Buy limit order (visible on the order receipt and on Explorer) | H5: Not Run
A6: LO-02 | B6: Place sell limit order | C6: High | D6: Functional | E6: Wallet has ERC-20 balance | F6: 1. Click 'Limit' tab 2. Set sell token, buy token 3. Enter an exact amount into the Sell token field 4. set a limit price 5. Click 'Place limit order' 6. Sign in wallet" | G6: 1. Sell limit order placed 2. shown in orders table. Order type is a Sell limit order (visible on the order receipt and on Explorer) | H6: Not Run
A7: LO-03 | B7: Partially fillable order execution | C7: High | D7: Functional | E7: Partial fill enabled (default) | F7: 1. Place a limit order with amount >balance, set a price below a market one 2. Check the order type in the order receipt 3. Check the order execution | G7: The order has 'partially filable' in its type. Same info if dsiplayed on Explorer When an order is filled partially, the percentage is adjusted on the limit orders table. Order is still displayed in the Open tab unless it is Expires or cancelled | H7: Not Run
A8: LO-04 | B8: Fill-or-kill order toggle | C8: Medium | D8: Functional | E8: Limit order panel open | F8: 1. Open settings 2. Disable 'Partially fillable' 3. Place order | G8: The order has 'Fill or kill ' in its type. Same info if dsiplayed on Explorer | H8: Not Run | I8: Partial approvals (setting allowance to exact trade amount) are NOT supported for limit orders — full (unlimited) on-chain approval or gasless permit required. EOA and MM Smart Account: permit available. SC wallets: on-chain only.
A9: LO-05 | B9: Cancel limit order | C9: High | D9: Functional | E9: Open limit order exists | F9: 1. Locate order in open orders 2. Open burger menu for the order 3. click on cancel and confirm the action 3. Sign cancellation | G9: It is a soft cancellation. the order goes into the Cancelling state and them changes its status to 'Cancelled.', and moved to the History tab from Open In case an order is already included into auction, the order stilll might be filled, so the status will be updated accordingly | H9: Not Run
A10: LO-06 | B10: Limit order expiry (custom duration) | C10: Medium | D10: Functional | E10: Limit order panel open | F10: 1. Set order duration (e.g., 35 min) 2. Place order with a limit price that won't be filled 3. Wait for expiry | G10: 1. Order expires after set duration 2. removed from open orders automatically | H10: Not Run | I10: Min custom duration is 30 minutes
A11: LO-07 | B11: Surplus capture on limit order | C11: High | D11: Functional | E11: Market price better than limit price at fill time | F11: 1. Place limit order below market 2. Observe fill price | G11: 1. Fill price better than limit price 2. surplus forwarded to user | H11: Not Run
A12: LO-08 | B12: 'Executes at' traffic light indicator | C12: Medium | D12: UI | E12: Open limit order panel | F12: 1. View open orders 2. Check 'Executes at' column | G12: 1. Green/yellow/red indicator shown 2. hover tooltip explains distance from execution | H12: Not Run
A13: LO-09 | B13: Place limit order with 1-year expiry | C13: Low | D13: Functional | E13: Wallet connected | F13: 1. Set duration to max (1 year) 2. Place order | G13: Order accepted with 1-year validity | H13: Not Run
A14: LO-10 | B14: Price displayed in USD toggle | C14: Low | D14: UI | E14: Limit order panel open | F14: 1. Toggle limit price display between native token and USD | G14: Price updates correctly in both modes without calculation errors | H14: Not Run
A15: LO-11 | B15: Sell limit order: place with balance ≥ 1 gwei (minimum) | C15: High | D15: Functional | E15: Wallet has sell token balance ≥ 1 gwei; limit order tab active | F15: 1. Select sell token with exactly 1 gwei balance (or smallest practical amount) 2. Enter sell amount > balance 3. Set limit price 4. Place order | G15: Order is placed | H15: Not Run | I15: If a token balance is 0, order cannot be placed
A16: LO-12 | B16: Sell limit order: place multiple orders with same balance | C16: High | D16: Functional | E16: Wallet has ERC-20 sell token; sufficient balance for multiple orders | F16: 1. Place first limit sell order for 50% of balance at price X 2. Place3-4 more same orders | G16: All orders are placed | H16: Not Run | I16: Unlimited order placement: same balance can back multiple concurrent orders
A17: LO-13 | B17: Limit order: unfillable state — insufficient balance at execution time | C17: High | D17: Functional | E17: Active open limit order; sell token balance subsequently spent or reduced below order amount | F17: 1. Place a fill or kill limit sell order for 100 USDC 2. Transfer out or spend the USDC so balance drops below order amount 3. Observe order status / UI indicator | G17: 1. Order marked as 'unfillable' or shows warning indicator 2. not immediately cancelled (it can become fillable again if balance is restored) 3. clear visual indicator in open orders table | H17: Not Run | I17: Order remains open but solver skips it until balance is restored
A18: LO-14 | B18: Limit order: unfillable state — insufficient allowance | C18: High | D18: Functional | E18: Active limit order; token approval subsequently revoked (e.g. via revoke.cash) | F18: 1. Place a limit order for an ERC-20 2. Revoke the token approval for CoW Protocol 3. Observe order status in the open orders table | G18: 1. Order shown as unfillable due to insufficient allowance 2. warning displayed 3. order not cancelled automatically 4. re-approving token restores fillability | H18: Not Run | I18: Partial approvals (setting allowance to exact trade amount) are NOT supported for limit orders — full (unlimited) on-chain approval or gasless permit required. EOA and MM Smart Account: permit available. SC wallets: on-chain only.
A19: LO-15 | B19: Limit order: unfillable state resolves when balance restored | C19: Medium | D19: Functional | E19: Order in unfillable state due to low balance | F19: 1. Start with order in unfillable state (from LO-16) 2. Top up sell token balance to cover order amount 3. Observe order status update | G19: 1. Order returns to normal active state 2. unfillable indicator cleared 3. eligible for next batch execution when price is reached | H19: Not Run
A20: LO-16 | B20: Orders table: navigate between Open, History tabs | C20: High | D20: Functional | E20: Wallet with orders in multiple states (open, filled, cancelled, expired) | F20: 1. Place at least one open order and have at least one order in History (filled, cancelled, or expired) 2. Open the orders table 3. Click the OPEN tab 4. Click the ORDERS HISTORY tab 5. Verify each tab shows the correct subset of orders | G20: 1. OPEN tab displays only currently open (active) orders 2. ORDERS HISTORY tab displays filled, cancelled, and expired orders 3. Tab switching is instant; no full page reload 4. Active tab is visually highlighted 5. Order counts match the actual orders for the connected wallet on the current chain | H20: Not Run
A21: LO-17 | B21: Orders table: three-dot menu actions per order | C21: Medium | D21: Functional | E21: Active open order in orders table | F21: 1. Hover over an open order row 2. Click the three-dot (⋮) menu 3. Verify available actions (Cancel, View on Explorer, order receipt.) | G21: 1. Three-dot menu shows relevant actions for order state: 'order receipt,' 'Cancel' for open orders, 'View on Explorer' for any order 2. actions execute correctly when selected | H21: Not Run
A22: LO-18 | B22: Orders table: order row shows current execution price | C22: Medium | D22: UI | E22: Open limit order in orders table | F22: 1. View open limit order in table 2. Check 'Executes at' column 3. Compare with set limit price | G22: 1. Current execution price shown (not just limit price) 2. traffic light color reflects proximity to execution 3. hovering shows tooltip with how far price needs to move | H22: Not Run | I22: Per spec: traffic light system — green/yellow/red based on current network fees and market price
A23: LO-19 | B23: Orders table: invert price display per order | C23: Low | D23: UI | E23: Open limit order visible in table | F23: 1. Click on the 'Executes at' price field for a specific order 2. Observe price direction change | G23: 1. Price display inverts for that individual order (e.g. ETH/USDC ↔ USDC/ETH) 2. hover text also reflects the inverted direction 3. other orders unaffected | H23: Not Run | I23: Per spec: 'Clicking on that field will invert the price display for the individual order'
A24: LO-20 | B24: Cancel limit order: off-chain soft cancellation (EOA) | C24: High | D24: Functional | E24: EOA wallet; active limit order | F24: 1. Locate open limit order in orders table 2. Click the ⋮ menu → 'Cancel order' 3. Sign the off-chain cancellation message in wallet (if available) 4. Observe order status | G24: 1. Off-chain cancellation message signed 2. order status changes to 'Cancelling' then 'Cancelled' 3. no gas TX on-chain 4. immediate effect — solvers stop attempting to fill the order | H24: Not Run | I24: Off-chain cancellation is gas-free for EOA. SC wallets cannot do off-chain soft cancellation — they must use on-chain TX
A25: LO-21 | B25: Cancel limit order: on-chain cancellation (EOA) | C25: High | D25: Functional | E25: EOA wallet; active limit order | F25: 1. Locate open limit order 2. Click cancel 3. Select on-chain cancellation option 4. Confirm and pay gas in wallet | G25: 1. On-chain cancellation TX submitted 2. gas paid 3. order cancelled with on-chain guarantee 4. order moves to 'cancelling' state | H25: Not Run | I25: On-chain cancellation is final and cannot be front-run
A26: LO-22 | B26: Cancel limit order: SC wallet — on-chain TX required (no soft cancel) | C26: High | D26: Functional | E26: Safe or other SC wallet; active limit order | F26: 1. Open orders table with SC wallet connected 2. Click cancel on a limit order 3. Observe cancellation flow | G26: 1. Only on-chain TX option available for SC wallets 2. Safe TX created in queue 3. requires threshold signatures 4. no off-chain soft cancellation available for SC wallets | H26: Not Run | I26: SC wallets cannot sign off-chain cancellation messages — on-chain is the only path
A27: LO-23 | B27: Cancel all orders: EOA wallet — bulk cancel via UI | C27: High | D27: Functional | E27: EOA wallet; 3+ active limit orders open | F27: 1. Navigate to the open orders table 2. Look for 'Cancel all' or bulk cancel option 3. Click Cancel all 4. Sign the cancellation (off-chain for all orders at once) | G27: 1. 'Cancel all' option available for EOA wallets 2. all open limit orders cancelled in a single off-chain signing action 3. no per-order gas 4. all orders status → Cancelled (if not filled: the cancellation is a soft one) | H27: Not Run | I27: Cancel all is EOA-only feature using off-chain signatures. SC wallets must cancel each order individually via on-chain TX
A28: LO-24 | B28: Cancel all orders: SC wallet — no bulk cancel available | C28: Medium | D28: Functional | E28: Safe or SC wallet; multiple active limit orders | F28: 1. Open orders table with SC wallet connected 2. Check whether 'Cancel all' option is present | G28: 1. 'Cancel all' option NOT available for SC wallets 2. each order must be cancelled individually via separate on-chain TXs 3. each cancellation requires threshold signatures in Safe | H28: Not Run
A29: LO-25 | B29: Recreate limit order from expired or cancelled order | C29: High | D29: Functional | E29: At least one felled, expired or cancelled limit order in history | F29: 1. Navigate to order history (filled, Cancelled or Expired tab) 2. Locate a limit order 3. Click 'Recreate order' in the menu or on order receipt 4. Verify form is pre-filled with original order parameters 5. Adjust if needed and place the order | G29: 1. Recreate option available on filled/expired/cancelled orders 2. clicking pre-fills the Limit order form with original: sell token, buy token, limit price, order type (sell/buy), fill mode 3. user can adjust before placing 4. new order placed as fresh order | H29: Not Run | I29: Recreate is a UX shortcut — should not copy the expired order ID, only its parameters
A30: LO-26 | B30: Limit order: gasless partial permit makes order unfillable — unfillable label shown | C30: High | D30: Functional | E30: EOA or MM Smart Account; open limit order for token X placed with gasless permit; a subsequent gasless partial permit for smaller amount signed for same token | F30: 1. Place limit order for 500 USDC (sign gasless permit for 500 USDC) 2. Place a market swap for 50 USDC with gasless permit for 50 USDC only 3. Return to Limit orders tab / orders table 4. Observe limit order status | G30: 1. Limit order labeled unfillable 2. unfillable indicator visible in open orders table 3. order not cancelled 4. tooltip or inline message indicates cause (insufficient allowance) 5. order stays unfillable until allowance is restored via on-chain approval | H30: Not Run | I30: Cross-reference MO-71. Both swap and limit orders are affected by partial permit side-effects.
A31: LO-27 | B31: Limit order: on-chain approval restores unfillable permit order | C31: High | D31: Functional | E31: Limit order unfillable due to insufficient permit allowance (from LO-31) | F31: 1. Locate unfillable limit order 2. Execute on-chain approval for the sell token (sufficient amount) 3. Confirm approval TX in wallet 4. Observe limit order status update | G31: 1. After on-chain approval TX confirms, limit order status reverts to normal/fillable 2. unfillable indicator removed 3. order eligible for execution when limit price is reached 4. no need to recreate the order | H31: Not Run | I31: On-chain approval is the definitive fix — signing another permit may not reliably fix the order.
A32: LO-28 | B32: Limit order: gasless permit not available for SC wallets — on-chain only | C32: High | D32: Functional | E32: Safe or Base Smart Account connected; placing a limit order for permit-compatible token | F32: 1. Connect SC wallet (Safe or Base SA) 2. Open Limit tab 3. Select permit-compatible sell token 4. Observe approval options when placing the order | G32: 1. No gasless permit option shown for limit order approval in SC wallet context 2. on-chain approval TX required 3. Safe TX queue used for approval 4. partial permit side-effect warning NOT shown (since permits not available for SC wallets) | H32: Not Run | I32: Permit matrix applies equally to limit orders: EOA ✓ MM SA ✓ SC wallets ✗
A33: LO-29 | B33: FOK unfillable: balance drops below full order amount | C33: High | D33: Functional | E33: Fill-or-kill (FOK) limit order active; sell token balance initially sufficient; sufficient allowance set | F33: 1. Place FOK limit order for 100 USDC (full balance required for FOK) 2. Transfer out USDC so balance = 99 USDC (any amount below 100) 3. Observe the order in the open orders table | G33: 1. Order labeled unfillable 2. unfillable indicator shown in orders table 3. balance below full order amount is sufficient to trigger unfillable state for FOK 4. order not cancelled — restoring balance above order amount removes unfillable label | H33: Not Run | I33: FOK rule: balance < order sell amount → unfillable. Partially fillable threshold: order becomes unfillable when both balance AND allowance drop below 0.05% of the sell amount. For FOK: any shortfall in balance OR allowance (whichever is less than the full order amount) makes the order unfillable.
A34: LO-30 | B34: FOK unfillable: allowance drops below full order amount | C34: High | D34: Functional | E34: FOK limit order active; sufficient balance; allowance subsequently reduced below full order amount (e.g. via revoke.cash partial revocation or a new partial permit) | F34: 1. Place FOK limit order for 100 USDC 2. Reduce allowance to 99 USDC (set allowance below order amount) 3. Observe order status in orders table | G34: 1. Order labeled unfillable 2. allowance below full order amount is sufficient to trigger unfillable for FOK 3. balance unaffected 4. restoring full allowance (on-chain approval) removes unfillable label | H34: Not Run | I34: FOK rule: allowance < order sell amount → unfillable. Partially fillable threshold: order becomes unfillable when both balance AND allowance drop below 0.05% of the sell amount. For FOK: any shortfall in balance OR allowance (whichever is less than the full order amount) makes the order unfillable.
A35: LO-31 | B35: FOK unfillable: both balance and allowance below full order amount | C35: Medium | D35: Functional | E35: FOK limit order active; both balance and allowance subsequently reduced below order amount | F35: 1. Place FOK limit order for 100 USDC 2. Reduce balance to 80 USDC AND reduce allowance to 70 USDC 3. Observe order status | G35: 1. Order labeled unfillable 2. both conditions independently satisfy unfillable rule for FOK 3. single unfillable indicator shown (not doubled) 4. order requires BOTH balance ≥ 100 AND allowance ≥ 100 to become fillable again | H35: Not Run | I35: FOK rule: balance < order amount OR allowance < order amount → unfillable. Either shortfall alone is enough. Partially fillable threshold: order becomes unfillable when both balance AND allowance drop below 0.05% of the sell amount. For FOK: any shortfall in balance OR allowance (whichever is less than the full order amount) makes the order unfillable.
A36: LO-32 | B36: Partially fillable unfillable: balance drops below 0.05% of sell amount | C36: High | D36: Functional | E36: Partially fillable limit order active (default mode); sell token balance initially sufficient | F36: 1. Place partially fillable limit order for 1000 USDC (0.05% threshold = 0.50 USDC) 2. Reduce balance to 0.49 USDC (below 0.05% of 1000) 3. Observe order status in orders table 4. Also verify: balance at exactly 0.50 USDC (threshold boundary) → order still fillable | G36: 1. Order labeled unfillable when balance < 0.05% of sell amount (0.50 USDC for a 1000 USDC order) 2. at exactly the threshold (0.50 USDC) order remains fillable 3. unfillable label appears only below the threshold 4. restoring balance above 0.05% of sell amount removes unfillable label | H36: Not Run | I36: Partially fillable rule: balance < 0.05% of sell amount → unfillable. This is a much lower threshold than FOK (which requires full order amount). Example: 1000 USDC order → threshold = 0.50 USDC. Partially fillable threshold: order becomes unfillable when both balance AND allowance drop below 0.05% of the sell amount. For FOK: any shortfall in balance OR allowance (whichever is less than the full order amount) makes the order unfillable.
A37: LO-33 | B37: Partially fillable unfillable: allowance drops below 0.05% of sell amount | C37: High | D37: Functional | E37: Partially fillable limit order active; allowance subsequently reduced below 0.05% of sell amount | F37: 1. Place partially fillable limit order for 1000 USDC (0.05% threshold = 0.50 USDC) 2. Reduce allowance to 0.49 USDC (below threshold) 3. Observe order status 4. Verify: allowance at exactly 0.50 USDC → order still fillable | G37: 1. Order labeled unfillable when allowance < 0.05% of sell amount 2. at exactly threshold order remains fillable 3. balance unaffected 4. restoring allowance above threshold removes unfillable label | H37: Not Run | I37: Partially fillable rule: allowance < 0.05% of sell amount → unfillable. Partially fillable threshold: order becomes unfillable when both balance AND allowance drop below 0.05% of the sell amount. For FOK: any shortfall in balance OR allowance (whichever is less than the full order amount) makes the order unfillable.
A38: LO-34 | B38: Partially fillable unfillable: both balance and allowance below 0.05% threshold | C38: Medium | D38: Functional | E38: Partially fillable limit order active; both balance and allowance reduced below 0.05% of sell amount | F38: 1. Place partially fillable limit order for 1000 USDC 2. Reduce balance to 0.30 USDC AND allowance to 0.20 USDC (both below 0.50 threshold) 3. Observe order status | G38: 1. Order labeled unfillable 2. single unfillable indicator shown 3. order requires both balance ≥ 0.05% AND allowance ≥ 0.05% of sell amount to become fillable 4. either condition alone being above threshold is not sufficient — both must be met | H38: Not Run | I38: Partially fillable rule: balance < 0.05% of sell amount AND allowance < 0.05% → unfillable. Contrast with FOK where either condition alone triggers unfillable. Partially fillable threshold: order becomes unfillable when both balance AND allowance drop below 0.05% of the sell amount. For FOK: any shortfall in balance OR allowance (whichever is less than the full order amount) makes the order unfillable.
A39: LO-35 | B39: Partially fillable: only balance OR allowance below 0.05% threshold — still fillable | C39: High | D39: Functional | E39: Partially fillable limit order active | F39: 1. Place partially fillable limit order for 1000 USDC (threshold = 0.50 USDC) 2. Scenario A: reduce balance to 0.30 USDC but keep allowance ≥ 0.50 USDC 3. Observe order — should still be fillable 4. Scenario B: reduce allowance to 0.30 USDC but keep balance ≥ 0.50 USDC 5. Observe order — should still be fillable | G39: 1. Order remains fillable in both scenarios 2. partially fillable requires BOTH balance AND allowance to be below 0.05% to become unfillable 3. if only one is below the threshold the order can still partially fill using whichever resource is available 4. no unfillable label shown in either scenario | H39: Not Run | I39: Key distinction from FOK: partially fillable order needs BOTH conditions met simultaneously to be unfillable. FOK needs only ONE. Partially fillable threshold: order becomes unfillable when both balance AND allowance drop below 0.05% of the sell amount. For FOK: any shortfall in balance OR allowance (whichever is less than the full order amount) makes the order unfillable.
A40: LO-36 | B40: Unfillable labeling: FOK vs partially fillable — different threshold behavior | C40: High | D40: Functional | E40: Two concurrent limit orders for same token: one FOK, one partially fillable; balance = 0.5% of sell amount | F40: 1. Place FOK order for 1000 USDC 2. Place partially fillable order for 1000 USDC 3. Reduce balance to 0.30 USDC (below 0.05% threshold) AND reduce allowance to 0.30 USDC 4. Observe both orders in the table simultaneously 5. Now restore balance to 1.00 USDC but keep allowance at 0.30 USDC 6. Observe both orders again | G40: 1. Step 4: Both orders unfillable (FOK: balance < full amount; partially fillable: both below 0.05%) 2. Step 6 (balance restored to 1.00, allowance still 0.30): FOK remains unfillable (allowance 0.30 < 1000 order amount) 3. partially fillable remains unfillable (allowance 0.30 < 0.05% threshold of 0.50) 4. different thresholds clearly distinguishable in UI labels | H40: Not Run | I40: This test confirms the two rules coexist correctly on the same orders table. FOK threshold = full order amount; partially fillable threshold = 0.05% of sell amount.
... A42: LO-38 | B42: Limit order: 0-decimal token (MPS on Gnosis Chain) — limit price, amount, balance | C42: High | D42: Functional | E42: Wallet connected on Gnosis Chain; MPS (0-decimal) balance available; Limit tab active | F42: 1. Switch to Gnosis Chain 2. Select MPS as sell token on Limit tab 3. Enter sell amount as whole integer (e.g. 100 MPS) 4. Attempt fractional input (e.g. 0.5 MPS) → observe behavior 5. Set limit price; verify price display 6. Check balance shown for MPS in sell field 7. Place order; verify order appears in table with correct integer amounts | G42: 1. MPS sell amount accepts only whole integers 2. fractional input rejected or clamped 3. balance shown as integer 4. limit price and USD estimations calculated without decimal scaling errors 5. placed order shows integer sell amount in orders table 6. minimum order check uses 1 gwei correctly scaled for 0-decimal token (1 gwei of a 0-decimal token = 1 whole token, not 0.000000001) | H42: Not Run | I42: MPS is a 0-decimal ERC-20 on Gnosis Chain. The UI must not allow fractional input (e.g. 0.5 MPS) and must display balance and amounts as whole integers. USD estimation must multiply by token price without decimal shifting errors. Note: 1 gwei minimum for limit orders = 1 whole MPS token for a 0-decimal token.
A43: LO-39 | B43: Limit orders table: not connected user — no tabs shown | C43: High | D43: Functional | E43: No wallet connected; Limit orders page open | F43: 1. Open swap.cow.fi/#/1/limit/ without connecting a wallet 2. Observe the orders table area | G43: 1. Orders table does not show any tabs (no OPEN / ORDERS HISTORY / SIGNING / UNFILLABLE tabs) 2. table shows empty/connect prompt only | H43: Not Run
A44: LO-40 | B44: Limit orders table: unsupported network — no tabs + Unsupported network message | C44: High | D44: Functional | E44: Wallet connected to an unsupported network; Limit page open | F44: 1. Connect wallet to unsupported network 2. Open Limit orders page 3. Observe orders table | G44: 1. Orders table does not show any tabs 2. Unsupported network message is displayed on the table | H44: Not Run
A45: LO-41 | B45: Limit orders table: supported network — no orders — OPEN default + ORDERS HISTORY clickable | C45: High | D45: Functional | E45: Wallet connected to a supported network; no orders placed yet | F45: 1. Connect wallet to a supported network 2. Navigate to Limit orders page 3. Observe default active tab 4. Click ORDERS HISTORY tab | G45: 1. OPEN tab shown and active by default with empty state (content not changed) 2. ORDERS HISTORY tab is clickable and content is not changed when navigated to (empty state) | H45: Not Run
A46: LO-42 | B46: Limit orders table: EOA wallet places order — appears in OPEN tab + navigation to OPEN | C46: High | D46: Functional | E46: EOA wallet (MetaMask/Rabby/etc.) connected; user is on another tab (e.g. ORDERS HISTORY) | F46: 1. Be on ORDERS HISTORY or other tab 2. Place or recreate a limit order 3. Sign in wallet 4. Observe which tab is active and where the order appears | G46: 1. Order appears in the OPEN tab 2. user is navigated to the OPEN tab even if they were on another tab before placement | H46: Not Run
A47: LO-43 | B47: Limit orders table: EOA places unfillable order — OPEN tab + UNFILLABLE tab appears | C47: High | D47: Functional | E47: EOA wallet connected; user places a fill-or-kill limit order where sell amount > wallet balance (immediately unfillable) | F47: 1. Be on any tab other than OPEN 2. Place an unfillable FOK order (sell amount > balance) 3. Observe table after placement | G47: 1. Order appears in OPEN tab 2. additional UNFILLABLE tab appears to the right of the OPEN tab 3. user is navigated to the OPEN tab after placement (not UNFILLABLE) | H47: Not Run
A48: LO-44 | B48: Limit orders table: unfillable order becomes fillable — removed from UNFILLABLE — stays on OPEN | C48: Medium | D48: Functional | E48: Open order in UNFILLABLE state; user is currently on UNFILLABLE tab | F48: 1. Have unfillable order visible on UNFILLABLE tab 2. Restore balance/allowance so order becomes fillable 3. Observe table | G48: 1. Order removed from UNFILLABLE tab 2. order still displayed on OPEN tab 3. if no more unfillable orders UNFILLABLE tab is no longer displayed 4. user navigated to OPEN tab if they were on UNFILLABLE | H48: Not Run
A49: LO-45 | B49: Limit orders table: partially filled order stays on OPEN tab | C49: Medium | D49: Functional | E49: Open partially-fillable limit order; at least one partial fill occurs | F49: 1. Place a partially fillable limit order 2. Let at least one partial fill occur 3. Observe order location in table | G49: Order is still displayed on the OPEN tab | H49: Not Run
A50: LO-46 | B50: Limit orders table: fully filled order moved to ORDERS HISTORY — no navigation | C50: High | D50: Functional | E50: Open limit order; order becomes fully filled | F50: 1. Have an open limit order 2. Let the order be fully filled 3. Observe table | G50: 1. Order is no longer displayed on the OPEN tab 2. order is moved to the ORDERS HISTORY tab 3. no navigation — user stays where they are | H50: Not Run
A51: LO-47 | B51: Limit orders table: open order becomes unfillable — UNFILLABLE tab appears — no navigation | C51: Medium | D51: Functional | E51: Open fillable limit order; balance/allowance subsequently drops below unfillable threshold | F51: 1. Have an open fillable order 2. Reduce balance or allowance so order becomes unfillable 3. Observe table | G51: 1. Order still displayed on OPEN tab 2. UNFILLABLE tab appears to the right of OPEN tab with this order 3. no navigation — user stays where they are | H51: Not Run
A52: LO-48 | B52: Limit orders table: cancelling order shows Cancelling status on OPEN tab | C52: High | D52: Functional | E52: Open limit order exists; user initiates cancellation | F52: 1. Click cancel on open limit order 2. Sign the cancellation request 3. Observe the order row on OPEN tab | G52: Order is still displayed on the OPEN tab with Cancelling status as soon as request is signed | H52: Not Run
A53: LO-49 | B53: Limit orders table: cancelled order moved to ORDERS HISTORY — no navigation | C53: High | D53: Functional | E53: Limit order in Cancelling state; cancellation is confirmed | F53: 1. Wait for cancelling order to be confirmed as cancelled 2. Observe table | G53: 1. Order not on OPEN tab 2. order moved to ORDERS HISTORY tab 3. no navigation — user stays where they are | H53: Not Run
A54: LO-50 | B54: Limit orders table: cancelling order gets filled — moved to ORDERS HISTORY — no navigation | C54: Medium | D54: Functional | E54: Limit order in Cancelling state; order gets filled before cancel is finalized (race condition) | F54: 1. Initiate order cancellation (soft cancel) 2. Order fills before cancellation is processed 3. Observe table | G54: 1. Order not on OPEN tab 2. moved to ORDERS HISTORY as Filled 3. no navigation — user stays where they are | H54: Not Run
... A59: LO-55 | B59: USDT approval: revoke-then-approve flow for limit order when existing allowance < order amount (Ethereum) | C59: High | D59: Functional | E59: EOA wallet on Ethereum Mainnet; existing USDT allowance for CoW Protocol is non-zero but less than the order amount (e.g. 2 USDT approved, ordering 4 USDT) | F59: 1. Connect EOA wallet on Ethereum Mainnet 2. Navigate to the Limit tab 3. Select USDT as sell token (verify existing allowance is 2 USDT) 4. Enter a sell amount that exceeds the existing allowance (e.g. 4 USDT) 5. Observe the approval UI — should show a 2-step approval flow, not a single approve 6. Click the approval action 7. Sign the first transaction (approve(0) to revoke existing allowance) 8. Wait for the revoke TX to confirm on-chain 9. Sign the second transaction (approve(amount) for the new amount) 10. Wait for the approve TX to confirm 11. Place the limit order as normal | G59: 1. UI displays a 2-step approval flow specific to USDT (revoke first, then approve) 2. First TX is approve(0) sent to USDT contract — sets allowance to 0 3. Revoke TX confirms successfully on-chain 4. Second TX is approve(newAmount) — sets allowance to the required amount 5. Approve TX confirms successfully (does not fail like a single-step approve would) 6. Limit order can be placed and submitted normally after both TXs confirm 7. No 'approval failed' error encountered 8. Verify on revoke.cash that the final allowance equals the requested amount | H59: Not Run
A60: LO-56 | B60: USDT approval: no revoke or approve needed for limit order when existing allowance ≥ order amount | C60: Medium | D60: Functional | E60: existing USDT allowance for CoW Protocol is zero or more than an order amount | F60: 1. Connect EOA wallet on Ethereum Mainnet 2. Navigate to the Limit tab 3. Select USDT as sell token (verify existing allowance is e.g. 100 USDT) 4. Enter a sell amount ≤ existing allowance (e.g. 4 USDT) 5. Observe approval UI 6. Proceed with the limit order | G60: 1. No approval prompt shown — existing allowance is sufficient 2. No revoke TX requested 3. No approve TX requested 4. Limit order proceeds directly to signing/placement 5. USDT allowance is not modified | H60: Not Run | I60: Verifies the 2-TX flow is correctly skipped when not needed. USDT-specific behavior should not impose unnecessary transactions.
A61: LO-57 | B61: Limit Settings: Custom Recipient toggle visible in settings panel | C61: Medium | D61: UI | E61: Limit tab open; settings (gear) icon visible | F61: 1. Open Limit tab on swap.cow.fi/#/1/limit 2. Click the settings icon next to 'My orders' 3. Observe the 'Limit Settings' section | G61: 1. Settings panel opens with 'Limit Settings' and 'Limit Interface' sections 2. 'Custom Recipient' toggle is shown with an info (?) tooltip 3. Toggle is OFF by default | H61: Not Run
A62: LO-58 | B62: Limit Settings: Enable Partial Executions toggle (per-order default) | C62: High | D62: Functional | E62: Limit settings panel open | F62: 1. Toggle 'Enable Partial Executions' OFF 2. Place a limit order and check the Partially fillable indicator on the order 3. Toggle 'Enable Partial Executions' ON again and place another order | G62: 1. With toggle OFF new limit orders are placed as Fill-or-Kill (not partially fillable) 2. With toggle ON new limit orders are partially fillable 3. Setting persists across reloads | H62: Not Run
A63: LO-59 | B63: Limit Settings: Lock Limit Price toggle | C63: Medium | D63: Functional | E63: Limit settings panel open | F63: 1. Toggle 'Lock Limit Price' ON, set a limit price 2. Change the market price (e.g. wait or switch tokens) and observe the limit price field 3. Toggle 'Lock Limit Price' OFF and observe whether the limit price follows the market when sell/buy amount changes | G63: 1. With toggle ON the limit price stays fixed even when sell/buy amounts or market change; padlock icon next to limit price reflects locked state 2. With toggle OFF the limit price is recalculated/derived from market and amount changes 3. Setting persists across reloads | H63: Not Run
A64: LO-60 | B64: Limit Interface: Desktop — Left-Aligned Orders Table toggle | C64: Low | D64: UI | E64: Limit settings panel open on desktop viewport | F64: 1. Toggle 'Desktop: Left-Aligned Orders Table' ON 2. Observe the orders table layout below the order form 3. Toggle OFF and observe | G64: 1. With toggle ON the orders table is aligned to the left of the viewport on desktop 2. With toggle OFF the orders table returns to the default centered layout 3. Setting persists across reloads | H64: Not Run
A65: LO-61 | B65: Limit Interface: Limit Price Position dropdown (Top/Bottom) | C65: Low | D65: UI | E65: Limit settings panel open | F65: 1. Open the 'Limit Price Position' dropdown 2. Select 'Top' and observe the order form 3. Select 'Bottom' (default) and observe | G65: 1. Two options available: Top, Bottom (default Bottom) 2. When 'Top' is selected the 'When 1 TOKEN is worth' price block is rendered above the sell/buy cards 3. When 'Bottom' is selected the price block stays below the sell/buy cards (default) 4. Setting persists across reloads | H65: Not Run
A66: LO-62 | B66: Limit: send final outcome to Custom Recipient — recipient field & warning | C66: High | D66: Functional | E66: Wallet connected; Limit tab open; 'Custom Recipient' toggle enabled in settings | F66: 1. Enable 'Custom Recipient' in Limit settings 2. A 'Recipient' field appears between the buy token card and the limit price block with 'Wallet Address or ENS name' placeholder and a Paste button 3. Paste a valid recipient address (different from the connected wallet) or an ENS name 4. Configure a valid limit order (sell token, buy token, amount, price) 5. Click 'Place limit order' and sign | G66: 1. Recipient field is shown when Custom Recipient is enabled 2. App validates the address (ENS resolves) 3. A warning is shown informing the user that the bought tokens will be sent to the specified external recipient address — funds cannot be recovered if the address is wrong 4. Confirmed orders settle the bought amount to the custom recipient instead of the connected wallet | H66: Not Run | I66: ENS name is supported on Ethreum and Sepolia chains only
A67: LO-63 | B67: Limit: Custom Recipient — invalid address rejected | C67: Medium | D67: Negative | E67: Custom Recipient enabled on Limit tab | F67: 1. Enter an invalid address (e.g. '0x123', random text, or a non-existent ENS) 2. Attempt to place the limit order | G67: 1. Address is rejected / marked as invalid 2. Place limit order button is disabled or submission is blocked until a valid address or ENS is provided | H67: Not Run
A68: LO-64 | B68: Limit: selling a native token (ETH) is not supported | C68: High | D68: Negative | E68: Limit tab open on Ethereum (or any chain whose native token is ETH) | F68: 1. Try to select the native token (ETH on Mainnet, xDAI on Gnosis, etc.) as the SELL token via the token selector 2. Observe the token list and selection behavior 3. If the native token was preselected via URL, observe the form state | G68: 1. Native token is selectable as the sell token on the Limit page. Watning explanation that limit orders support only ERC-20 sell tokens — wrap to WETH ir pick ETH is displayed | H68: Not Run
A69: LO-65 | B69: Limit order: protocol volume fee 0.02% (2 bps) on standard token pair | C69: High | D69: Functional | E69: Wallet connected; Limit tab open; standard non-correlated pair selected (e.g. WETH → USDC); limit price set in-market so order is fillable immediately | F69: 1. Open Limit tab on swap.cow.fi 2. Select a standard pair (WETH → USDC) 3. Configure a sell amount and an in-market limit price 4. Review the order summary / costs breakdown 5. Identify the Protocol fee line item before signing | G69: 1. Order summary shows a 'Protocol fee' component 2. Protocol fee ≈ Volume × 0.0002 (2 bps) 3. Fee is denominated in the surplus token (buy token for sell-side limit orders) 4. Final receive amount = expected receive − protocol fee − any other costs | H69: Not Run | I69: Per docs (Volume Fee, Standard Assets): Volume × 0.0002 = 0.02%. Volume Fee applies to ALL orders. Out-of-market limit orders additionally incur the surplus-based fee (50% of surplus, capped at 0.98%) — that is a separate case.
A70: LO-66 | B70: Limit order: protocol volume fee 0.003% (0.3 bps) on correlated assets (stables/RWAs) | C70: High | D70: Functional | E70: Wallet connected; Limit tab open; correlated pair selected (e.g. USDC → USDT or DAI → USDC); in-market limit price set | F70: 1. Open Limit tab on swap.cow.fi 2. Select a correlated pair (USDC → USDT) 3. Configure sell amount and an in-market limit price 4. Review order summary / costs breakdown 5. Identify the Protocol fee line item 6. Repeat with another stable/RWA correlated pair (e.g. DAI → USDC) | G70: 1. Order summary shows 'Protocol fee' component 2. Protocol fee ≈ Volume × 0.00003 (0.3 bps) 3. Fee denominated in surplus token 4. Fee value is ~6.67× smaller than the standard 2 bps tier on equivalent volume | H70: Not Run | I70: Per docs (Volume Fee, Correlated Assets — Stables/RWAs): Volume × 0.00003 = 0.003%. Applies regardless of in/out-of-market status. Out-of-market orders additionally incur surplus fee separately.

Sheet TWAPOrders
A1: TWAP Order Tests
A2: CoW Swap | swap.cow.fi | TWAPOrders
A4: ID | B4: Test Name | C4: Priority | D4: Type | E4: Preconditions | F4: Test Steps | G4: Expected Result | H4: Status | I4: Notes / Defect ID
A5: TW-01 | B5: Place TWAP order (Safe wallet) | C5: High | D5: Functional | E5: Safe wallet connected (inside app or using WC); fallback handler upgraded; min $1k per part (Mainne, 1 use ither chainst) | F5: 1. Open TWAP tab 2. Set sell token, total amount 3. Configure parts & duration 4. Review & sign in Safe | G5: 1. TWAP order created 2. parts visible 3. first part executes at scheduled time | H5: Not Run
A6: TW-02 | B6: TWAP minimum order size enforcement | C6: High | D6: Negative | E6: Safe wallet | F6: 1. Attempt TWAP with <$1k per part on Mainnet or 1 USD on other L2s | G6: Error or warning preventing order below minimum threshold | H6: Not Run
A7: TW-03 | B7: TWAP price protection option | C7: High | D7: Functional | E7: TWAP order being configured | F7: 1. Open TWAP confirm modal and read default 'Price protection' value 2. Set min (0%) and max (99.99%) and intermediate values (e.g. 5%, 25%) 3. Verify 'Minimum receive' updates: Min receive ≈ Expected receive × (1 − price protection) 4. Verify 'Limit price (incl. fees)' updates accordingly (worse than Rate by the protection band) 5. Place the TWAP and confirm the signed values match the displayed Min receive | G7: 1. Default price protection = 10% 2. Accepted range: min 0%, max 99.99% (rejects negative and >=100%) 3. Minimum receive = Expected receive × (1 − price_protection); updates live 4. Limit price (incl. fees) reflects the protection band (per the image: Rate 1 WETH = 2116.6998 USDT, Limit 1 WETH = 2135.1112 USDT at 10% protection) 5. Signed order's minimum receive matches the value shown before signing | H7: Not Run
A8: TW-04 | B8: Cancel TWAP order (multisig) | C8: High | D8: Functional | E8: Active TWAP order from Safe | F8: 1. Click cancel on TWAP order in the order menu 2. Collect required Safe signatures 3. Execute cancellation tx | G8: 1. Cancellation tx created in Safe 2. unfilled parts cancelled after all signatures | H8: Not Run
A9: TW-05 | B9: TWAP inaccessible without Safe wallet | C9: Medium | D9: Negative | E9: Non-Safe wallet connected (e.g. MetaMask) | F9: 1. Attempt to access TWAP tab | G9: 1. UI prompts user to use/create Safe wallet 2. Action butoon shows 'unsupporte wallet' | H9: Not Run
A10: TW-06 | B10: TWAP: Safe wallet with incompatible/no fallback handler — upgrade prompt shown | C10: High | D10: Functional | E10: Safe wallet connected; fallback handler NOT set or set to incompatible handler | F10: 1. Connect Safe without correct fallback handler 2. Open TWAP tab 3. Attempt to place TWAP order | G10: 1.warning to set up a FB handler is shown 2. user prompted to upgrade Safe fallback handler 3. upgrade CTA links to documentation 4. TWAP order is placed: set up a FB handler TX is included into the batch | H10: Not Run
A11: TW-07 | B11: TWAP: fallback handler upgrade flow | C11: High | D11: Functional | E11: TWAP order is placed with a TX to set up a FB handler in it | F11: try placing another TWAP order | G11: No messge to setup another FB handler appears | H11: Not Run | I11: Upgrade has undergone auditing; link to audit: github.com/cowprotocol/composable-cow
A12: TW-08 | B12: TWAP: WalletConnect-connected Safe — order placement works | C12: Medium | D12: Functional | E12: Safe connected via WalletConnect (not as Safe App); correct fallback handler installed | F12: 1. Connect Safe via WalletConnect to swap.cow.fi 2. Open TWAP tab 3. Configure TWAP order 4. Sign via Safe interface | G12: 1. TWAP available 2. order signing routed through Safe WC session 3. Safe TX queue updated 4. TWAP executes correctly | H12: Not Run
A13: TW-09 | B13: TWAP: order receipt shows execution details | C13: Medium | D13: Functional | E13: Active TWAP order placed | F13: 1. Open orders overview 2. Locate TWAP order 3. Click to view order receipt | G13: Order receipt displays: total amount, number of parts, part duration, price protection setting, execution status per part, TX details for executed parts | H13: Not Run
A14: TW-10 | B14: TWAP: individual part three-dot menu actions | C14: Medium | D14: Functional | E14: Active TWAP order with at least one part visible | F14: 1. Expand TWAP parent row in orders table 2. Click three-dot menu on an individual part 3. Verify available actions | G14: 1. Part-level actions available (e.g. view on explorer , order receipt and cancle order for Open part) 2. parent-level actions (cancel for open order, order receipt ) in parent three-dot menu 3. actions correctly scoped to part vs whole order | H14: Not Run
A15: TW-11 | B15: Cancel TWAP order: on-chain only — no off-chain soft cancel | C15: High | D15: Functional | E15: Active TWAP order from Safe | F15: 1. Open orders table with TWAP order visible 2. Click ⋮ → Cancel 3. Observe cancellation flow | G15: 1. TWAP cancellation is always on-chain (no soft/off-chain option) 2. Safe TX created in queue for cancellation 3. requires all threshold signatures 4. no gas-free cancel option shown for TWAP | H15: Not Run | I15: TWAP orders are on-chain programmatic orders (ComposableCoW) — they can only be cancelled via on-chain TX
A16: TW-12 | B16: Cancel individual TWAP part: per-part cancel available when part is in Open status | C16: Medium | D16: Functional | E16: Active TWAP order with multiple parts; some parts already executed | F16: 1. Place a TWAP order with multiple parts 2. Wait for at least one part to become Open (active) 3. Expand the TWAP parent row in the orders table 4. Click ⋮ menu on an individual part that is in Open status 5. Select 'Cancel' for that part 6. Execute the on-chain cancellation TX in Safe 7. Verify: that part cancelled; other parts unaffected | G16: 1. Individual part cancellation available when the part status is Open 2. cancellation is on-chain (Safe TX required) 3. cancelled part removed from execution schedule 4. remaining Open parts continue executing on their schedule 5. already-Filled parts are unaffected and final | H16: Not Run | I16: Any order (parent TWAP or individual part) can be cancelled while in Open status. Cancelling the parent cancels all remaining Open parts at once. Cancelling an individual part cancels only that part.
A17: TW-13 | B17: Cancel TWAP: partially executed — only remaining parts cancelled | C17: Medium | D17: Functional | E17: TWAP order with at least 1 part already executed; remaining parts unfilled | F17: 1. Wait for at least 1 TWAP part to execute 2. Cancel the TWAP order 3. Execute cancellation TX in Safe 4. Verify state | G17: 1. Already-executed parts remain filled and unaffected 2. only remaining/pending parts are cancelled 3. order history shows partial execution 4. tokens from filled parts already in wallet | H17: Not Run
A18: TW-14 | B18: TWAP part unfillable: balance below part sell amount | C18: High | D18: Functional | E18: Active TWAP order with Safe wallet; at least one part in Open/scheduled state; Safe balance of sell token sufficient initially; e.g. TWAP total = 1000 USDC across 5 parts → each part = 200 USDC | F18: 1. Place TWAP order: 1000 USDC split into 5 parts (200 USDC each) 2. Wait for a part to become active (Open) 3. Reduce Safe balance to 199 USDC (below the 200 USDC part amount) 4. Observe the active part status in the orders table | G18: 1. The active TWAP part labeled unfillable 2. unfillable indicator shown on the part row in the expanded TWAP orders table 3. part not skipped permanently — if balance is restored above 200 USDC before the part's time window expires, it becomes fillable again 4. other scheduled parts unaffected until they become active | H18: Not Run
A19: TW-15 | B19: TWAP part unfillable: allowance below part sell amount | C19: High | D19: Functional | E19: Active TWAP order; part amount = 200 USDC; allowance subsequently reduced below 200 USDC (e.g. via a new partial permit or on-chain allowance reduction) | F19: 1. Active TWAP with part amount = 200 USDC 2. Reduce token allowance for CoW Protocol to 199 USDC 3. Observe the active part status 4. Restore allowance to ≥ 200 USDC via on-chain approval 5. Observe status update | G19: 1. Part labeled unfillable when allowance < part amount (199 < 200) 2. unfillable indicator shown on the part row 3. after on-chain approval restores allowance ≥ 200 USDC, part returns to fillable state 4. gasless permit cannot be used to restore allowance for Safe (on-chain approval only) | H19: Not Run | I19: TWAP parts are treated as FOK: a part is unfillable when balance < part amount OR allowance < part amount. The 0.05% partial-fill threshold used for partially fillable limit orders does NOT apply to TWAP parts. Note: Safe wallet cannot sign gasless permits — on-chain approval is the only way to restore allowance for a TWAP order.
A20: TW-16 | B20: TWAP part unfillable: both balance and allowance below part amount | C20: Medium | D20: Functional | E20: Active TWAP order; part amount = 200 USDC; both balance and allowance reduced below 200 USDC | F20: 1. Active TWAP with part amount = 200 USDC 2. Reduce balance to 150 USDC AND reduce allowance to 100 USDC 3. Observe active part status 4. Restore only balance to 200 USDC (leave allowance at 100) 5. Observe whether part becomes fillable 6. Also restore allowance to ≥ 200 USDC 7. Observe final status | G20: 1. Step 3: part unfillable (both below part amount) 2. Step 5: part remains unfillable — balance alone is not enough, allowance still insufficient 3. Step 7: part becomes fillable once both balance ≥ 200 AND allowance ≥ 200 4. single unfillable indicator shown throughout (not doubled) | H20: Not Run | I20: TWAP parts are treated as FOK: a part is unfillable when balance < part amount OR allowance < part amount. The 0.05% partial-fill threshold used for partially fillable limit orders does NOT apply to TWAP parts. FOK rule: balance < part amount OR allowance < part amount → unfillable. BOTH must be restored to ≥ part amount for the part to become fillable again.
A21: TW-17 | B21: TWAP order: part amounts and USD estimations correct for tokens with different decimal precision | C21: High | D21: Functional | E21: Safe wallet connected with fallback handler; tokens with varying decimals: e.g. WETH (18 dec) sell, USDC (6 dec) buy | F21: 1. Open TWAP tab 2. Select WETH (18 dec) sell → USDC (6 dec) buy 3. Enter total sell amount; configure parts and duration 4. Verify 'Sell per part' and 'Buy per part' read-only fields 5. Check USD estimation for total and per-part amounts 6. Repeat with WBTC (8 dec) sell → USDC (6 dec) buy | G21: 1. Sell per part = total sell amount / number of parts, correctly scaled for token decimals 2. Buy per part ≈ Expected receive / number of parts at the displayed Rate; rounded to buy-token precision 3. USD estimation for total and per-part amounts consistent and correctly scaled 4. Minimum part size check ($1k Mainnet / $5 Gnosis Chain / $1 other L2s) uses USD value, not raw token units 5. Sum of per-part amounts equals total sell amount (any rounding residual absorbed by the last part) | H21: Not Run | I21: Common precision combinations to cover: 18-decimal (ETH, WETH, DAI, COW) × 6-decimal (USDC, USDT) × 8-decimal (WBTC) × 0-decimal (MPS on Gnosis Chain). MPS (MetaPool Staking token) has 0 decimals — the smallest tradeable unit IS 1 whole token; no fractional amounts possible. USD estimations must use correct decimal scaling for each token.
A22: TW-18 | B22: TWAP order: 0-decimal token (MPS on Gnosis Chain) — part amounts, minimum, USD estimation | C22: High | D22: Functional | E22: Safe wallet on Gnosis Chain with fallback handler; MPS (0-decimal) balance available in Safe | F22: 1. Switch to Gnosis Chain; open TWAP tab 2. Select MPS as sell token 3. Enter total sell amount as whole integer (e.g. 100 MPS) 4. Set number of parts (e.g. 5) → verify 'Sell per part' = 20 MPS (integer) 5. Attempt total amount not evenly divisible by parts (e.g. 101 MPS ÷ 5) 6. Verify minimum part size check uses USD value of MPS correctly 7. Check USD estimation for total and per-part values | G22: 1. Sell per part shown as whole integer (e.g. 20 MPS, not 20.000...) 2. non-divisible total: UI handles gracefully (rounds down, shows warning, or adjusts parts) 3. USD estimation per part = integer MPS amount × MPS/USD price without decimal errors 4. minimum part size ($5 on Gnosis Chain) validated against USD value of integer MPS parts 5. no fractional MPS amounts anywhere in the TWAP configuration | H22: Not Run | I22: MPS is a 0-decimal ERC-20 on Gnosis Chain. The UI must not allow fractional input (e.g. 0.5 MPS) and must display balance and amounts as whole integers. USD estimation must multiply by token price without decimal shifting errors.
A23: TW-19 | B23: TWAP orders table: not connected user — no tabs shown | C23: High | D23: Functional | E23: No wallet connected; TWAP/Advanced orders page open | F23: 1. Open swap.cow.fi/#/1/advanced/ without connecting wallet 2. Observe orders table | G23: 1. Orders table does not show any tabs | H23: Not Run
A24: TW-20 | B24: TWAP orders table: unsupported network — no tabs + Unsupported network message | C24: High | D24: Functional | E24: Wallet connected to an unsupported network; TWAP page open | F24: 1. Connect wallet to unsupported network 2. Open Advanced/TWAP orders page 3. Observe orders table | G24: 1. Orders table shows no tabs 2. Unsupported network message displayed on table | H24: Not Run
A25: TW-21 | B25: TWAP orders table: supported network — non-Safe wallet — same as no open orders state | C25: High | D25: Functional | E25: Non-Safe wallet (EOA/MetaMask/Rabby/Base SA) connected to a supported network | F25: 1. Connect a non-Safe wallet to supported network 2. Open Advanced/TWAP page 3. Observe orders table | G25: 1. Table behaves as the no open orders state | H25: Not Run
A26: TW-22 | B26: TWAP orders table: Safe connected — no orders — OPEN default + ORDERS HISTORY clickable | C26: High | D26: Functional | E26: Safe wallet connected to supported network; no TWAP orders placed yet | F26: 1. Connect Safe wallet 2. Navigate to Advanced/TWAP page 3. Observe default active tab 4. Click ORDERS HISTORY | G26: 1. OPEN tab active by default with empty content (not changed) 2. ORDERS HISTORY tab is clickable with unchanged empty content 3. same flow as Limit orders no-orders state | H26: Not Run
A27: TW-23 | B27: TWAP orders table: user places TWAP order — SIGNING tab appears + navigation to SIGNING | C27: High | D27: Functional | E27: Safe wallet connected; fallback handler installed; user on another tab (e.g. ORDERS HISTORY) | F27: 1. Be on any tab other than SIGNING 2. Place a TWAP order 3. Observe which tab appears and is active | G27: 1. Order appears in SIGNING tab 2. SIGNING tab appears to the left of OPEN (if not already shown) 3. user navigated to the SIGNING tab | H27: Not Run
A28: TW-24 | B28: TWAP orders table: signing order is signed and fillable — SIGNING removed + OPEN | C28: High | D28: Functional | E28: TWAP order in SIGNING; user on SIGNING tab; Safe tx executed and order is fillable | F28: 1. Complete Safe transaction signing 2. Order is deemed fillable 3. Observe table | G28: 1. Order removed from SIGNING tab 2. order appears on OPEN tab 3. SIGNING tab disappears if no more signing orders 4. user navigated to OPEN tab if they were on SIGNING | H28: Not Run
A29: TW-25 | B29: TWAP orders table: signing order is signed and unfillable — OPEN + UNFILLABLE tab | C29: High | D29: Functional | E29: TWAP order in SIGNING; Safe tx executed but order is unfillable | F29: 1. Complete Safe tx signing 2. Order is unfillable (insufficient balance/allowance) 3. Observe table | G29: 1. Order removed from SIGNING 2. appears on OPEN tab 3. UNFILLABLE tab appears to right of OPEN 4. user navigated to OPEN tab 5. SIGNING tab removed if no more signing orders | H29: Not Run
A30: TW-26 | B30: TWAP orders table: unfillable order/part becomes fillable — UNFILLABLE removed — navigated to OPEN | C30: Medium | D30: Functional | E30: TWAP order/part in UNFILLABLE state; user is on UNFILLABLE tab; balance/allowance restored | F30: 1. Have TWAP part in UNFILLABLE (user on UNFILLABLE tab) 2. Restore balance/allowance above part amount 3. Observe table | G30: 1. Order removed from UNFILLABLE tab 2. order still displayed on OPEN tab 3. if no more unfillable orders UNFILLABLE tab disappears 4. user navigated to OPEN if they were on UNFILLABLE | H30: Not Run
A31: TW-27 | B31: TWAP orders table: partially filled — stays on OPEN — pending parts show SCHEDULED status | C31: Medium | D31: Functional | E31: Active TWAP order on OPEN tab; one or more parts have been executed | F31: 1. Place TWAP order with multiple parts 2. Let at least one part execute 3. Observe parent order and individual part statuses | G31: 1. Parent order still displayed on OPEN tab 2. not-yet-started/executed parts show Scheduled status (TWAP-specific additional status not present in Limit orders) | H31: Not Run
A32: TW-28 | B32: TWAP orders table: all parts filled (or last part fills) — order moved to ORDERS HISTORY — no navigation | C32: High | D32: Functional | E32: Active TWAP order; all parts have been executed | F32: 1. Let all TWAP parts fill (or let the last part fill) 2. Observe table after last fill | G32: 1. Order no longer on OPEN tab 2. moved to ORDERS HISTORY tab 3. no navigation — user stays where they are | H32: Not Run
A33: TW-29 | B33: TWAP orders table: user cancels parent TWAP order — shows Cancelling status on OPEN | C33: High | D33: Functional | E33: Active TWAP parent order; user initiates full order cancellation | F33: 1. Click cancel on TWAP parent order 2. Sign the on-chain Safe cancellation tx 3. Observe order row on OPEN tab | G33: Order still displayed on OPEN tab with Cancelling status as soon as the cancellation request is signed | H33: Not Run
A34: TW-30 | B34: TWAP orders table: cancelling last part of TWAP — shows Cancelling on OPEN | C34: Medium | D34: Functional | E34: TWAP order with only last part remaining; user cancels that last part | F34: 1. Have only last TWAP part remaining in Open state 2. Cancel the last part 3. Sign on-chain Safe tx 4. Observe | G34: Order still displayed on OPEN tab with Cancelling status (because it is the last remaining part) | H34: Not Run
... A40: TW-36 | B40: TWAP orders table: expired non-last part — parent stays on OPEN with Open status | C40: Medium | D40: Functional | E40: TWAP order with multiple parts; a non-last part time window expires without fill | F40: 1. Have TWAP order with multiple parts 2. Let a non-last part expire 3. Observe table | G40: 1. Parent order still displayed on OPEN tab with Open status 2. expired part removed from schedule 3. remaining Scheduled/Open parts continue as normal | H40: Not Run
A41: TW-37 | B41: TWAP part status: SCHEDULED shown for pending parts when parent is OPEN | C41: High | D41: Functional | E41: Active TWAP parent order on OPEN tab; multiple parts configured; at least one part is currently active | F41: 1. Place TWAP order with 5 parts 2. Let first part become active (Open) 3. Observe status of remaining 4 parts | G41: 1. Parts not yet started show Scheduled status in the expanded TWAP parts view 2. this SCHEDULED status is TWAP-specific and does not exist in Limit orders 3. the currently executing part shows Open status | H41: Not Run | I41: TWAP-specific additional status per spec. TWAP parts have SCHEDULED status when a parent is OPEN but the part has not yet started executing
A42: TW-38 | B42: USDT approval: revoke-then-approve flow for TWAP order when existing allowance < order amount (Ethereum) | C42: High | D42: Functional | E42: existing USDT allowance for CoW Protocol is non-zero but less than the order amount (e.g. 2 USDT approved, ordering 2000 USDT); | F42: 1. Navigate to the TWAP tab 2. Select USDT as sell token (verify existing allowance is 2 USDT) 3. Enter a sell amount that exceeds the existing allowance (e.g. 2000 USDT) 4. Observe the approval UI — should show a 2-step approval flow, not a single approve 5. Place the TWAP order as normal | G42: 1. UI displays a 2-step approval flow specific to USDT (revoke first, then approve) 2. 2 transactions are included into the bundle: First TX is approve(0) sent to USDT contract — sets allowance to 0 Second TX is approve(newAmount) — sets allowance to the required amount | H42: Not Run
A43: TW-39 | B43: USDT approval: no revoke or approve needed for TWAP order when existing allowance ≥ order amount | C43: Medium | D43: Functional | E43: existing USDT allowance for CoW Protocol is zero or more than an order amount | F43: 1. Navigate to the TWAP tab 2. Select USDT as sell token 3. Enter a sell amount ≤ existing allowance 4. Proceed with the TWAP order | G43: 1. No approval prompt shown — existing allowance is sufficient 2. No revoke TX requested 3. No approve TX requested 4. Twap order proceeds directly to signing/placement 5. USDT allowance is not modified | H43: Not Run
A44: TW-40 | B44: TWAP Settings: Custom Recipient toggle visible in settings panel | C44: Medium | D44: UI | E44: TWAP tab open; settings (gear) icon visible | F44: 1. Open TWAP tab on swap.cow.fi/#/1/advanced 2. Click the settings icon next to 'My orders' 3. Observe 'TWAP Settings' section | G44: 1. Settings panel opens 2. 'Custom Recipient' toggle is shown with an info (?) tooltip 3. Toggle is OFF by default | H44: Not Run
A45: TW-41 | B45: TWAP Settings: TWAP Interface — Desktop: Left-Aligned Orders Table toggle | C45: Low | D45: UI | E45: TWAP settings panel open on desktop viewport | F45: 1. Toggle 'Desktop: Left-Aligned Orders Table' ON 2. Place a TWAP order (or use Safe with existing orders) so the orders table is rendered 3. Toggle OFF again and observe | G45: 1. With toggle ON the orders table is aligned to the left of the viewport on desktop 2. With toggle OFF the orders table returns to the default centered/right-aligned layout 3. Setting persists across reloads | H45: Not Run
A46: TW-42 | B46: TWAP: send final outcome to Custom Recipient — recipient field & warning | C46: High | D46: Functional | E46: Safe wallet connected; TWAP tab open; 'Custom Recipient' toggle enabled in settings | F46: 1. Enable 'Custom Recipient' in TWAP settings 2. A 'Recipient' field appears between the buy token card and rate section with 'Wallet Address or ENS name' placeholder and a Paste button 3. Paste a valid recipient address (different from connected wallet) 4. Configure a valid TWAP (sell token, parts, duration, price protection) 5. Click 'Review & sign' / Place TWAP order | G46: 1. Recipient field shown when Custom Recipient is enabled 2. App validates the address (ENS supported) 3. A warning banner is displayed informing the user that the final outcome (bought tokens) will be sent to the specified external recipient and to make sure the address is correct (cannot be undone) 4. After confirmation, filled parts settle to the custom recipient address, not the connected Safe | H46: Not Run | I46: ENS name is supported on Ethreum and Sepolia chains only
A47: TW-43 | B47: TWAP: Custom Recipient — invalid address rejected | C47: Medium | D47: Negative | E47: Custom Recipient enabled on TWAP tab | F47: 1. Enter an invalid address (e.g. '0x123', random text, or a non-existent ENS) 2. Try to place the TWAP order | G47: 1. Address is rejected / shown as invalid 2. Place order button is disabled or the form blocks submission until a valid address or ENS is provided | H47: Not Run
A48: TW-44 | B48: TWAP: only sell order type supported (no buy mode) | C48: High | D48: Functional | E48: TWAP tab open | F48: 1. Open TWAP tab on swap.cow.fi/#/1/advanced 2. Compare the form to the Limit tab where 'Buy' mode is available (Sell/Receive at least toggling) 3. Try to enter an amount into the buy-token field | G48: 1. TWAP form only exposes a 'Sell' amount input — the buy-side amount is calculated/derived (Receive incl. fees) 2. The buy token field is read-only with respect to the order type — only the receive estimation is displayed | H48: Not Run
A49: TW-45 | B49: TWAP: selling a native token (ETH) is not supported | C49: High | D49: Negative | E49: TWAP tab open; Safe connected on Ethereum (or any chain whose native token is ETH/xDAI/etc.) | F49: 1. Try to select the native token (ETH on Mainnet) as the SELL token via the token selector 2. Observe the token list and selection behavior | G49: 1. Minimum is 2 parts (TWAP requires at least two parts) 2. Maximum is 100 parts (per CoW spec); values above are clamped or rejected 3. Sell per part = total sell amount / parts; Buy per part ≈ Expected receive / parts; both update live on every change 4. If part size falls below the minimum-per-part threshold ($1k Mainnet / $5 Gnosis / $1 other L2s) the Place TWAP order button is disabled with a warning 5. Spinner accepts only integers; non-numeric or 0/1 entries are rejected/normalised | H49: Not Run
A50: TW-46 | B50: TWAP: No. of parts control — min/max enforcement | C50: Medium | D50: Functional | E50: TWAP form being configured | F50: 1. Open the 'Total duration' selector and pick a preset (e.g. 1 Hour) 2. Verify 'Part duration' = Total duration / No. of parts 3. Enter a custom Total duration and change No. of parts; verify Part duration recalculates live 4. Drive Part duration below 5 minutes (e.g. Total 8m / 2 parts = 4m) and verify warning 5. Drive Total duration to/above 1 year and verify it is rejected/clamped (parity with Limit order max) | G50: 1. Part duration = Total duration / No. of parts (e.g. 10m / 2 parts → 5m, matching the confirm modal in the reference image) 2. Part duration updates automatically when either Total duration or No. of parts changes 3. Custom total durations supported per UI 4. Minimum part duration is 5 minutes; below it a warning is displayed and order is not allowed 5. Maximum Total duration is 1 year (parity with Limit order) | H50: Not Run
A51: TW-47 | B51: TWAP: Total duration & Part duration — relationship | C51: Medium | D51: Functional | E51: TWAP form being configured with No. of parts = N | F51: 1. Open the 'Total duration' selector and pick a value (e.g. 1 Hour) 2. Observe 'Part duration' 3. Change 'Total duration' and 'No. of parts' to new values 4. check min part duration 5. max part duraiton | G51: 1. Part duration = Total duration / No. of parts (e.g. 1h / 2 parts → 30m) 2. Part duration updates automatically when either Total duration or No. of parts changes 3. Custom total durations are supported per UI; very short part durations show a warning 4. min part duration is 5 minutes: if it is less, than a warning is displayed. 5. same as for a limit order duraiton - 1 year | H51: Not Run
A52: TW-48 | B52: TWAP order: protocol volume fee 0.02% (2 bps) on standard token pair | C52: High | D52: Functional | E52: Wallet connected; TWAP tab open; standard non-correlated pair selected (e.g. WETH → USDC); valid TWAP configured (sell amount, parts, total duration) | F52: 1. Open TWAP tab on swap.cow.fi/#/1/advanced 2. Select a standard pair (WETH → USDC) 3. Configure a valid TWAP order (e.g. parts=4, duration=1h) 4. Review the order summary / costs breakdown for each part and totals 5. Identify the Protocol fee on each part and on the aggregate order | G52: 1. Order summary shows a Protocol fee component on each filled part and/or in aggregate 2. Protocol fee ≈ filled-volume × 0.0002 (2 bps) per part 3. Fee is denominated in the surplus token (buy token for sell-side TWAP) 4. Aggregate fee across all parts ≈ total filled volume × 0.0002 | H52: Not Run | I52: Per docs (Volume Fee, Standard Assets): Volume × 0.0002 = 0.02%. Volume Fee applies to ALL orders including TWAP. Discrete TWAP parts that are out-of-market at generation may additionally incur the surplus fee — separate case.
A53: TW-49 | B53: TWAP order: protocol volume fee 0.003% (0.3 bps) on correlated assets (stables/RWAs) | C53: High | D53: Functional | E53: Wallet connected; TWAP tab open; correlated pair selected (e.g. USDC → USDT or DAI → USDC); valid TWAP configured | F53: 1. Open TWAP tab on swap.cow.fi/#/1/advanced 2. Select a correlated pair (USDC → USDT) 3. Configure a valid TWAP (e.g. parts=4, duration=1h) 4. Review costs breakdown per part and aggregate 5. Identify Protocol fee per part 6. Repeat with another stable/RWA correlated pair (e.g. DAI → USDC) | G53: 1. Order summary shows Protocol fee on each filled part 2. Protocol fee per part ≈ part-volume × 0.00003 (0.3 bps) 3. Aggregate fee ≈ total filled volume × 0.00003 4. Fee is ~6.67× smaller than the standard 2 bps tier on equivalent volume | H53: Not Run | I53: Per docs (Volume Fee, Correlated Assets — Stables/RWAs): Volume × 0.00003 = 0.003%. Applies to TWAP parts of correlated-asset pairs as classified by CoW Protocol.
A54: TW-50 | B54: TWAP confirm modal: amount-calculation summary (Sell/part, Buy/part, Min receive, Rate, Limit price incl fees, durations, Start time) | C54: High | D54: Functional | E54: Safe wallet connected; TWAP configured with N parts (e.g. 2), Total duration (e.g. 10m), valid sell amount | F54: 1. Open the TWAP confirm modal 2. Read: Sell amount, Receive (before fees), Rate, Protocol fee, Safe App License Fee, Network costs, Expected receive, Price protection, Minimum receive, Limit price (incl. fees), Rewards code 3. Read the 'TWAP order split in N equal parts' block: Sell per part (1/N), Buy per part (1/N), Start time first part (1/N), Part duration, Total duration 4. Verify each value against its formula (see Expected) | G54: 1. Sell per part = Sell amount / N 2. Buy per part ≈ Expected receive / N (rounded to buy-token precision) 3. Part duration = Total duration / N; Start time first part = Now 4. Minimum receive = Expected receive × (1 − price protection) 5. Rate = USD-derived indicative price; Limit price (incl. fees) is worse than Rate by the price-protection band 6. Reference values from the image (3.7052 USDT → 0.00175 WETH, 2 parts, 10% protection): Sell/part 1.8526 USDT, Buy/part ≈0.000868 WETH, Part 5 min, Total 10 min, Min receive 0.001735 WETH | H54: Not Run | I54: Reference image shows Safe App confirm modal with all calculation fields
A55: TW-51 | B55: TWAP: Rate vs Limit price (incl. fees) — price-protection band | C55: High | D55: Functional | E55: TWAP configured; confirm modal open showing Rate and Limit price (incl. fees) | F55: 1. Note default price protection (10%); read Rate and Limit price (incl. fees) 2. Change price protection to 0% and re-read Limit price 3. Change to 50% then 99.99% and re-read Limit price each time 4. Toggle the price unit (sell/buy denomination) and confirm both Rate and Limit price flip consistently | G55: 1. Rate is the indicative price (e.g. 1 WETH = 2116.6998 USDT in the reference image) 2. At 0% protection: Limit price ≈ Rate (only the small fee adjustment remains) 3. Limit price always represents a worse rate for the taker than Rate (more sell required per unit of buy / less buy per unit of sell) 4. At 10% protection on the reference image: Rate 1 WETH = 2116.6998 USDT, Limit price 1 WETH = 2135.1112 USDT (≈ +0.87% wider than Rate, matching the fee-adjusted protection band) 5. Price-unit toggle keeps both values mathematically equivalent (reciprocal) | H55: Not Run | I55: Verify exact formula direction with product: Limit price = Rate × (1 + protection adjustment in sell-denominated view) and the inverse for buy-denominated view.
A56: TW-52 | B56: TWAP: Minimum receive calculation across price-protection edge values | C56: High | D56: Functional | E56: TWAP configured with a valid order and confirm modal open | F56: 1. Set price protection = 0% and record Minimum receive 2. Set price protection = 10% (default) and verify Min receive against the reference image (0.001735 WETH for 0.001737 WETH expected, i.e. ~0.1% buffer due to display rounding) 3. Set price protection = 99.99% and verify Min receive collapses to near-zero (but >0) 4. Verify Min receive units = buy-token units; USD estimation updates in sync | G56: 1. At 0%: Minimum receive ≈ Expected receive (only rounding) 2. At 10%: Minimum receive = Expected receive × (1 − 0.10), matches displayed value 3. At 99.99%: Minimum receive ≈ Expected receive × 0.0001 (>0) 4. Per-part minimum applied uniformly: each part inherits the same limit price, so aggregate Min receive ≈ N × per-part minimum | H56: Not Run | I56: Compare 0.001735 vs 0.001737 reference values — the ~0.1% gap is below 10% because the modal also rounds; check raw signed order for the exact bound.
A57: TW-53 | B57: TWAP: Receive (before fees) vs Expected receive — fee aggregation on the buy side | C57: High | D57: Functional | E57: Safe wallet connected; TWAP configured; confirm modal showing 'Receive (before fees)' and 'Expected to receive' | F57: 1. Read 'Sell amount', 'Receive (before fees)' and 'Rate' 2. Read 'Protocol fee', 'Safe App License Fee' and 'Network costs' (all denominated in buy token) 3. Read 'Expected to receive' 4. Compute: Receive(before fees) − (Protocol fee + Safe App License Fee + Network costs) and compare to Expected receive | G57: 1. Receive (before fees) ≈ Sell amount × Rate (in buy-token units) 2. All three fees are denominated in the buy token 3. Expected to receive = Receive (before fees) − Protocol fee − Safe App License Fee − Network costs (within display rounding) 4. USD estimates next to each row are consistent (sum-of-parts equals total within rounding) | H57: Not Run | I57: Exact fee % covered by TW-48 / TW-49 and Safe App License Fee cases — do not assert specific amounts here.
A58: TW-54 | B58: TWAP: fee line ordering and units on confirm modal | C58: Medium | D58: UI | E58: TWAP confirm modal open | F58: 1. Inspect the fee block order: Rate → Protocol fee → Safe App License Fee → Network costs → Expected to receive 2. Verify each fee row shows token amount, '+ gas' suffix where applicable (Network costs), and USD estimate 3. Hover the (i) tooltip on each fee row to confirm explanatory text loads | G58: 1. Fees appear in the documented order matching the reference image 2. All fees denominated in buy token; Network costs may include '+ gas' label 3. Tooltips open without errors and contain documentation links where appropriate | H58: Not Run | I58: Specific fee % covered by other cases (TW-48/TW-49 and Safe App fee cases).
A59: TW-55 | B59: TWAP: non-divisible split — per-part rounding and total reconciliation | C59: Medium | D59: Functional | E59: Safe wallet connected; TWAP configured with a total/parts combination that does not divide evenly (e.g. 10 USDC over 3 parts; or 1 wei over 3 parts on a high-decimal token) | F59: 1. Configure a non-divisible split (e.g. 10 USDC / 3 parts) 2. Read Sell per part on the confirm modal 3. Place the order and inspect per-part sell amounts in the orders table / signed payload 4. Repeat for a 0-decimal token (MPS on Gnosis Chain) where rounding is whole units | G59: 1. Sell per part is rounded down to the buy/sell token precision 2. Sum of per-part sell amounts equals the total sell amount exactly (any residual is absorbed by the last part) 3. No part has sell amount = 0 (otherwise the configuration is rejected before signing) 4. For 0-decimal tokens: each part is a whole-unit integer; non-divisible totals are either rejected or last part absorbs the residual | H59: Not Run | I59: ASSUMPTION: last-part residual absorption — confirm with product/source before running. Alternative implementations distribute residual to first part or split evenly with ceiling.
A60: TW-56 | B60: TWAP: per-part scheduling — Start time first part = Now, subsequent parts at Now + (k-1) × Part duration | C60: High | D60: Functional | E60: Safe wallet connected; TWAP configured with N=3 parts, Part duration = 5m, Total duration = 15m | F60: 1. Open the TWAP confirm modal 2. Read 'Start time first part (1/N)' value 3. Place the order and observe the orders table: scheduled times of parts 2/N and 3/N 4. Wait until part 1 fills/expires and confirm part 2 becomes active at the scheduled time | G60: 1. Start time first part is 'Now' on the confirm modal 2. After signing, part 1 is immediately active/open 3. Part k start time = order signed time + (k-1) × Part duration (parts 2..N show SCHEDULED until their start time) 4. Each part's valid-to = part start + Part duration; no overlap between parts | H60: Not Run | I60: Compare with TW-37 (SCHEDULED status). Reference image shows Start time first part = 'Now'.
A61: TW-57 | B61: TWAP: Rewards code (MOOOO) propagation across parent and each part | C61: Medium | D61: Functional | E61: Safe wallet connected with rewards (referrer) code active; TWAP configured with N parts | F61: 1. Open the TWAP confirm modal and verify 'Rewards code' = MOOOO 2. Place the order 3. Open the parent order details and each child part order details 4. Inspect appData / order metadata in the order receipt for each part | G61: 1. Rewards code value on confirm modal matches the active referrer code (MOOOO in the reference image) 2. Each part inherits the same Rewards code (visible on receipt / appData) 3. Parent TWAP receipt shows the same Rewards code as each part | H61: Not Run | I61: Compare with the corresponding market/limit-order rewards-code propagation cases.

Sheet CrossChain
A1: Cross-Chain Swap Tests
A2: CoW Swap | swap.cow.fi | CrossChain
A4: ID | B4: Test Name | C4: Priority | D4: Type | E4: Preconditions | F4: Test Steps | G4: Expected Result | H4: Status | I4: Notes / Defect ID
A5: CC-01 | B5: Cross-chain swap UI: accessible via Swap form | C5: High | D5: Functional | E5: Wallet connected on a supported source chain | F5: 1. Open swap.cow.fi 2. Locate the cross-chain / bridge option (tab or dropdown) 3. Verify it is accessible from the main Swap UI | G5: 1. Cross-chain swap option visible and accessible from main Swap form 2. UI clearly attributes the active bridge provider per route (Bungee for EVM<->EVM, Near Intents for non-EVM destinations) 3. Not confused with regular Swap (distinct route panel with two stops) | H5: Not Run | I5: Multiple providers exist (Bungee, Near Intents). Provider is auto-selected per route and the best price, not user-chosen. Verify provider name/logo shown in UI matches route (e.g. Bungee for Arb USDC -> Base DAI; Near Intents for Arb -> Solana/BTC/BNB-native).
A6: CC-02 | B6: Cross-chain swap: Near provider | C6: High | D6: Functional | E6: Wallet connected on Ethereum Mainnet; ETH or ERC-20 balance > 0 | F6: 1. Select source chain: Ethereum Mainnet 2. Select destination chain: BNB 3. Select sell and buy tokens 4. Enter amount 5. Verify recipient address shown (defaults to connected wallet) 6. Confirm and sign | G6: 1. Cross-chain order routed through the single bridge provider 2. tokens arrive on BNB 3. bridge TX hash shown for tracking | H6: Not Run
A7: CC-03 | B7: Cross-chain swap:Bungee provider | C7: High | D7: Functional | E7: Wallet connected on Arbitrum (or another Bungee-supported EVM chain); ERC-20 balance > 0 (e.g. USDC) | F7: 1. Source chain: Arbitrum; sell token: USDC 2. Destination chain: Base; buy token: DAI 3. Enter amount 4. Verify route panel shows 2 stops: 'Swap on CoW Protocol' then 'Bridge via Bungee' 5. Verify swap leg line items: Protocol fee, Network costs (est.), Expected to receive, Max. swap slippage (dynamic), Recipient, Min. to receive, Quote ID (Verified) 6. Verify 'Swap bridged via your Account Proxy: 0x...' banner with explorer link 7. Verify bridge leg line items: Est. bridge time, Bridge costs, Expected to receive, Min. to deposit, Recipient, Min. to receive 8. Click Confirm Swap and Bridge; sign | G7: 1. Order routed via Bungee provider 2. Account Proxy address shown as intermediate recipient on the swap leg 3. Final tokens received on Base at user's connected wallet (or custom recipient if set) 4. Bridge TX hash shown for tracking 5. Quote auto-refreshes every 15s while modal open | H7: Not Run | I7: Most likely, Bungee will be picked with these route selection. However, if Near provides the best quote, it will be picked automatically
A8: CC-04 | B8: Cross-chain: recipient address — defaults to connected wallet | C8: High | D8: Functional | E8: Cross-chain swap configured | F8: 1. Load a cross-chain swap 2. Check the recipient address field before confirming 3. Verify it is pre-filled with connected wallet address | G8: 1. Recipient defaults to connected wallet address 2. address is clearly visible to user before confirmation 3. no hidden or auto-changed recipient | H8: Not Run
A9: CC-05 | B9: Cross-chain: custom recipient address — valid address accepted | C9: High | D9: Functional | E9: Cross-chain swap form open Custom recipient option is switched ON in the settings | F9: 1. Change recipient to a different valid address on the destination chain 2. Verify address accepted 3. Confirm and execute swap | G9: 1. Custom recipient accepted 2. tokens arrive at the specified destination address (not connected wallet) 3. warning or confirmation prompt shown before placing order with non-self recipient | H9: Not Run | I9: Critical: verify funds go to correct address. Cross-chain transfers are typically irreversible
A10: CC-06 | B10: Cross-chain: recipient address — invalid address rejected | C10: High | D10: Negative | E10: "Cross-chain swap form open Custom recipient option is switched ON in the settings" | F10: 1. Enter an invalid address in recipient field (wrong format, wrong checksum, EVM address on non-EVM chain) 2. Attempt to proceed | G10: 1. Invalid address highlighted with error 2. swap cannot proceed 3. clear error message shown 4. user prompted to correct the address | H10: Not Run | I10: ENS names are not supported as a custom recipient for cross-chain swaps
A11: CC-07 | B11: Cross-chain: recipient address — wrong chain prefix warning | C11: High | D11: Functional | E11: Cross-chain swap form open; destination chain differs from recipient address prefix | F11: 1. Select destination chain (e.g. Arbitrum) 2. Enter recipient address with a different chain prefix (e.g. Ethereum address format when destination is Arbitrum, or base:0x... prefix) 3. Observe warning | G11: 1. Warning shown near recipient field indicating address prefix does not match destination chain 2. user prompted to verify before proceeding | H11: Not Run
A12: CC-08 | B12: Cross-chain: confirm modal shows recipient address prominently | C12: High | D12: Functional | E12: Cross-chain swap ready to confirm | F12: 1. Proceed to confirm modal for a cross-chain swap 2. Check that recipient address is displayed on the confirm modal | G12: 1. Recipient address clearly shown on confirm modal (not just at form stage) 2. user has final opportunity to verify before signing | H12: Not Run | I12: Verification at confirm stage is critical for cross-chain safety
A13: CC-09 | B13: Cross-chain: bridge provider shown in UI | C13: Medium | D13: Functional | E13: Cross-chain swap mode active | F13: 1. Open cross-chain swap 2. Look for provider attribution in the UI (logo, name, or 'Powered by' label) | G13: 1. Bridge provider name/logo clearly shown on the route panel (e.g. 'Bridge via Bungee' or 'Bridge via Near Intents') 2. Provider auto-selected per the best price 3. Single provider per quote (no manual switcher) - user can identify which service is routing the transfer | H13: Not Run | I13: Only one provider available — UI should make this clear so users know what they are using
A14: CC-10 | B14: Cross-chain: status tracking after submission | C14: Medium | D14: Functional | E14: Cross-chain swap submitted | F14: 1. Submit a cross-chain swap 2. Monitor status in the orders/activity view 3. Track through: initiated → bridging → completed states | G14: 1. Progress status shown at each stage 2. bridge TX hash linked 3. final 'completed' state shown when tokens arrive on destination chain 4. link to destination chain explorer where applicable | H14: Not Run
A15: CC-11 | B15: Cross-chain: unsupported chain pair shows clear error | C15: Medium | D15: Negative | E15: Cross-chain swap UI open | F15: 1. Attempt to select an unsupported source or destination chain 2. Or attempt an unsupported token pair across chains | G15: 1. No route or any other error appears on the form, it is not possible to place an order | H15: Not Run
A16: CC-12 | B16: Cross-chain: estimated fees and time shown before confirmation | C16: Medium | D16: Functional | E16: Cross-chain swap configured with valid token pair and amount | F16: 1. Configure cross-chain swap 2. Check fee breakdown and estimated bridge time before clicking confirm | G16: Swap leg shows: Protocol fee, Network costs (est.), Expected to receive, Max. swap slippage, Recipient, Min. to receive, Quote ID (Verified). Bridge leg shows: Est. bridge time, Bridge costs, Expected to receive, Min. to deposit, Recipient, Min. to receive. Form's 'Receive (incl. fees)' equals bridge Expected to receive. Header subtitle '(-X%)' is total quote slippage vs spot. User has full cost visibility before committing. | H16: Not Run
A17: CC-13 | B17: Cross-chain: single provider selected automatically — best price shown | C17: High | D17: Functional | E17: Cross-chain swap mode; valid token pair across two chains | F17: 1. Select a cross-chain route (e.g. Mainnet → Arbitrum, ETH → ETH) 2. Enter swap amount 3. Observe the provider section in the UI 4. Check whether one provider is auto-selected or multiple are presented for user choice | G17: 1. A single bridge provider is auto-selected by CoW Swap based on route and best price 2. No manual provider selection UI shown 3. Provider name/logo displayed | H17: Not Run | I17: CoW Swap picks the provider offering the best price automatically — users do not choose between providers. CC-15 is now obsolete and removed.
A18: CC-14 | B18: Cross-chain: provider quote updates when amount changes | C18: Medium | D18: Functional | E18: Cross-chain swap form open with a valid token pair | F18: 1. Enter a cross-chain swap amount 2. Observe provider and quoted receive amount 3. Change the sell amount (increase and decrease) 4. Observe whether the provider or quoted amount updates | G18: 1. Quote auto-refreshes every 30s; 'Quote refresh in N sec' countdown shown 2. On amount change, BOTH swap and bridge legs re-quote atomically; receive amount and fees update 3. If destination chain change makes another provider optimal, the auto-selected provider switches (e.g. Bungee -> Near Intents when switching dest to Solana) 4. No stale quote can be signed: quote must be fresh (within refresh window) | H18: Not Run | I18: Same as on Swaps
A19: CC-15 | B19: Cross-chain: ETH-flow source — native ETH sent cross-chain | C19: High | D19: Functional | E19: EOA wallet connected on Ethereum Mainnet; ETH balance > 0 | F19: 1. Select cross-chain mode 2. Set source chain: Ethereum Mainnet, sell token: ETH (native) 3. Set destination chain and buy token 4. Enter amount 5. Confirm and sign | G19: 1. Native ETH accepted as sell token for cross-chain swap without requiring WETH wrapping first 2. on-chain TX created for the bridge 3. ETH deducted from source 4. destination token received on target chain | H19: Not Run | I19: EOA wallet only — SC wallets may require wrapping ETH first before cross-chain swap
A20: CC-16 | B20: Cross-chain: ETH-flow source — SC wallet must wrap ETH first | C20: Medium | D20: Functional | E20: Safe or Base Smart Account connected; ETH in wallet; cross-chain mode | F20: 1. Connect SC wallet 2. Select cross-chain, ETH as sell token 3. Observe whether wrap step is required | G20: 1. SC wallet prompted to wrap ETH -> WETH before initiating cross-chain swap (no native ETH-flow for SC wallets) 2. Wrap TX appears in Safe queue if applicable 3. Cross-chain swap from SC wallet only succeeds when route uses Near Intents provider; Bungee routes are not supported for SC wallets | H20: Not Run | I20: Smart wallets (Safe / Base Smart Account) supported for cross-chain ONLY via Near Intents provider. Bungee swap-and-bridge does not support SC wallets at this time.
A21: CC-17 | B21: Cross-chain: swap to Solana — SOL or SPL token as destination | C21: High | D21: Functional | E21: Wallet connected on EVM chain; Solana wallet address available | F21: 1. Select a sell token 2. Set destination chain: Solana 3. Enter recipient Solana address (base58 format) 4. Select destination token (SOL or SPL token) 5. Review and confirm | G21: 1. Solana shown as selectable destination chain 2. Bridge leg shows 'Bridge via Near Intents' (Solana not supported by Bungee) 3. Recipient REQUIRED for Solana (no default); 'Send to Solana wallet' field with Paste button shown 4. Until recipient entered: primary button label 'Recipient is required for Solana' (disabled) 5. After valid base58 pasted but checkbox un-ticked: label 'Confirm recipient to swap' (disabled) 6. After 'Recipient is on Solana network. Confirm this is the correct address and that it exists on this chain.' checkbox ticked: button becomes 'Swap and Bridge' (enabled) 7. Tokens received in Solana wallet at specified address; amounts shown with SOL decimal precision (9) | H21: Not Run | I21: Non-EVM destination — address format differs from EVM 0x addresses. Verify address format validation handles base58
A22: CC-18 | B22: Cross-chain: Solana recipient — invalid base58 address rejected | C22: High | D22: Negative | E22: Destination chain: Solana | F22: 1. Enter an EVM-format (0x) address as Solana recipient 2. Enter a malformed base58 string 3. Observe validation | G22: 1. EVM address rejected for Solana destination 2. malformed base58 rejected 3. clear error message distinguishing EVM vs Solana address format | H22: Not Run
A23: CC-19 | B23: Cross-chain: swap to Bitcoin — BTC as destination | C23: High | D23: Functional | E23: Wallet connected on EVM chain; Bitcoin wallet address available (bech32 or legacy) | F23: 1. Select a sell token 2. Set destination chain: Bitcoin 3. Enter recipient Bitcoin address (bech32 format e.g. bc1q...) 4. Select BTC as buy token 5. Review and confirm | G23: 1. Bitcoin shown as selectable destination chain 2. Bridge leg uses Near Intents only (BTC not supported by Bungee) 3. BTC recipient (bech32 e.g. bc1q... or legacy) required and validated; no default 4. 'Recipient is on Bitcoin network. Confirm this is the correct address and that it exists on this chain.' checkbox required before swap can proceed 5. Bridge step shows 'Modified recipient address to: ...' (Near Intents deposit address) on swap leg, NOT Account Proxy 6. BTC received at specified address; amounts shown with BTC decimal precision (8); irreversibility warning shown | H23: Not Run | I23: Non-EVM destination with entirely different address format. Critical: BTC transactions irreversible
A24: CC-20 | B24: Cross-chain: Bitcoin recipient — invalid address rejected | C24: High | D24: Negative | E24: Destination chain: Bitcoin | F24: 1. Enter EVM address (0x...) as Bitcoin recipient 2. Enter malformed BTC address 3. Enter testnet BTC address (tb1...) when on mainnet 4. Observe validation for each | G24: 1. All invalid BTC addresses rejected 2. specific error for each case (wrong format, testnet vs mainnet mismatch) 3. cannot proceed until valid BTC mainnet address entered | H24: Not Run
A25: CC-21 | B25: Cross-chain: recipient warning for SC wallet or a smart wallet (base) | C25: High | D25: Functional | E25: SC wallet or a smart wallet (base) Cross-chain swap with custom recipient (different from connected wallet) | F25: 1. Set a cross-chain swap 2. Proceed to confirm modal 3. Check warning display | G25: 1. Prominent warning banner shown: 'Recipient <addr> is on <Network> network. Confirm this is the correct address and that it exists on this chain.' 2. Recipient address displayed prominently with explorer link 3. Explicit 'Confirm' checkbox must be ticked before primary button ('Approve, Swap & Bridge' or 'Swap and Bridge') becomes enabled 4. Warning persists across quote refresh; checkbox state does not reset on refresh unless recipient changes | H25: Not Run
A26: CC-22 | B26: Cross-chain: non-EVM destination recipient — format guidance shown | C26: High | D26: Functional | E26: Destination chain set to Solana or Bitcoin | F26: 1. Switch destination to Solana or Bitcoin 2. Observe recipient field placeholder and any helper text | G26: 1. Recipient field shows format hint appropriate for destination chain (e.g. 'Enter Solana address (base58)' or 'Enter Bitcoin address') 2. field validates correct format for chain | H26: Not Run
A27: CC-23 | B27: Cross-chain: price impact > 10% on swap step — confirm price modal shown | C27: High | D27: Functional | E27: Cross-chain swap configured with a token pair where the swap step results in > 15% price impact | F27: 1. Select a cross-chain swap with a large amount relative to available liquidity 2. Observe that price impact on the swap step exceeds 10% 3. Click 'Confirm Swap' 4. Observe additional confirmation step / modal | G27: 1. Confirm-price modal shown after clicking Confirm Swap 2. Price impact > xx% displayed prominently with red/warning styling 3. User must type 'Confirm' (or equivalent acknowledgement) before signing 4. Price impact applies to swap leg only; bridge leg has no PI concept (only Bridge costs and bridge slippage) 5. Bridging step does not proceed until swap step PI confirmation accepted | H27: Not Run | I27: Cross-chain price impact thresholds differ from regular swap thresholds. First known threshold: > 10% triggers confirm modal. Price impact applies to the swap step on the source chain, not the bridge step.
A28: CC-24 | B28: Cross-chain: price impact >=5% on swap step - acknowledgement modal shown | C28: High | D28: Functional | E28: Cross-chain swap configured where the swap step price impact is between 10% and 15% | F28: 1. Configure cross-chain swap with price impact at the second threshold level 2. Observe swap form before clicking Confirm 3. Check for warning banner and any change to the Confirm button state | G28: 1. Acknowledgement modal shown when PI >= 10% on the swap leg 2. User must check 'Swap anyway' (or equivalent) before signing | H28: Not Run
A29: CC-25 | B29: Cross-chain: sell/buy amounts and USD estimations correct for tokens with different decimal precision | C29: High | D29: Functional | E29: Wallet connected; cross-chain swap mode active; tokens with varying decimals available on source chain: e.g. ETH (18 dec) or WBTC (8 dec) as sell, USDC (6 dec) as buy on destination | F29: 1. Select ETH (18 dec) on Mainnet as sell token 2. Select USDC (6 dec) on Arbitrum as buy token 3. Enter sell amount; verify: - Sell USD estimation correct - Swap Min. to receive (intermediate token) correctly scaled - Expected deposit amount = Swap min. to receive - Bridge Min. to receive = Swap min. to receive − bridge cost - Buy USD estimation on destination chain correct 4. Repeat with WBTC (8 dec) sell → USDC (6 dec) buy cross-chain 5. Check bridge cost and estimated time displayed consistently | G29: All USD estimations and token amounts correctly scaled across decimal mismatch between source and destination tokens. Calculation invariants (verify on the route panel): - Swap.Expected_to_receive ~= Sell_amount * Price_swap - Network_costs - Protocol_fee - Swap.Min_to_receive = Swap.Expected_to_receive * (1 - swap_slippage) - Bridge.Min_to_deposit = Swap.Min_to_receive - Bridge.Expected_to_receive = Bridge.Min_to_deposit * Bridge_rate - Bridge_costs - Bridge.Min_to_receive = Bridge.Expected_to_receive * (1 - bridge_slippage) - Form 'Receive (incl. fees)' ~= Bridge.Expected_to_receive - Header subtitle '(-X%)' = total quote slippage vs spot No truncation or off-by-decimal errors at any step of the breakdown. | H29: Not Run | I29: Common precision combinations: 18-dec (ETH, WETH) × 6-dec (USDC, USDT) × 8-dec (WBTC) × 0-dec (MPS on Gnosis Chain). Cross-chain adds an extra dimension: source and destination tokens may have different decimals on different chains (e.g. USDC is 6-dec on Ethereum but may differ on other chains). USD estimations must use correct decimal scaling for both the swap step and the bridge step.
A30: CC-26 | B30: Cross-chain: 0-decimal token as source (MPS on Gnosis Chain) — amounts and USD estimation | C30: High | D30: Functional | E30: Wallet connected on Gnosis Chain; MPS (0-decimal ERC-20) balance available; cross-chain swap mode active with Gnosis Chain as source | F30: 1. Switch to Gnosis Chain; open cross-chain swap 2. Select MPS as sell token 3. Observe sell amount field — input should accept only whole integers 4. Enter a whole integer sell amount (e.g. 100 MPS) 5. Attempt fractional input (e.g. 0.5 MPS) → verify rejection or clamping 6. Select a destination chain and buy token 7. Verify USD estimation for sell amount correct (integer MPS × MPS price) 8. Verify swap step quote (intermediate token amount) correctly scaled 9. Verify bridge step quote and final destination amount consistent | G30: 1. MPS sell amount accepts only whole integers 2. fractional input rejected or clamped with clear indication 3. sell USD estimation = integer MPS amount × current MPS/USD price, no decimal shift 4. intermediate token amount (swap step output) correctly calculated from 0-decimal input 5. bridge step amounts consistent with swap step output 6. no decimal artifacts in any displayed field | H30: Not Run | I30: MPS is a 0-decimal ERC-20 on Gnosis Chain. As a source token: no fractional input allowed; amounts must be whole integers. USD estimation must scale correctly. Note: MPS as a cross-chain destination is only possible if the bridge provider supports it — verify availability first.
A31: CC-28 | B31: Cross-chain: Bungee - Account Proxy banner shown on swap leg | C31: Medium | D31: Functional | E31: specify a cross-chain swap with bungee | F31: 2. Locate the 'Swap bridged via your Account Proxy: 0x...' banner on the swap leg 3. Click the address link; verify it opens block explorer for source chain (Arbitrum) at the Account Proxy address | G31: 1. Account Proxy banner shown ONLY on Bungee swap leg 2. Address link opens correct block explorer for source chain at Account Proxy address | H31: Not Run | I31: Account Proxy is the user's CoW per-account contract on source chain used to forward funds to Bungee. Banner is informational and should be explorer-linked for trust.
A32: CC-29 | B32: Cross-chain: Near Intents - Modified recipient address banner shown on swap leg | C32: Medium | D32: Functional | E32: Specofy a cross-chain swap with Near | F32: 2. Locate 'Modified recipient address to: 0x...' banner on swap leg 3. Verify the address shown DIFFERS from the user's connected wallet (it is the Near intent deposit address on source chain) 4. Click the link; verify it opens block explorer for source chain 5. Refresh quote; verify address may differ across refreshes (each intent gets a fresh deposit address) | G32: 1. Modified recipient address banner shown ONLY on Near Intents swap leg 2. Address differs from connected wallet and is explorer-linked 3. Recipient field on swap leg matches the deposit address (e.g. 0x6ea1...8791 or 0xE7Bb...7475 in screenshots) | H32: Not Run | I32: Near Intents creates a per-intent deposit address. Swap leg sends to it; bridge leg picks it up and delivers to final user-specified destination address on target chain.
A33: CC-30 | B33: Cross-chain: calculation parity - form 'Receive (incl. fees)' equals bridge 'Expected to receive' | C33: High | D33: Functional | E33: Cross-chain swap configured with a stable quote | F33: 1. Configure Arb USDC -> Base DAI (Bungee); read 'Receive (incl. fees)' on form header 2. Expand route panel; read bridge step 'Expected to receive' and 'Min. to receive' 3. Verify form Receive == bridge Expected to receive (within rounding) 4. Verify form 'Min. to receive' == bridge Min. to receive 5. Repeat with Arb USDC -> Solana SOL (Near Intents) and Arb USDC -> BNB native (Near Intents) | G33: 1. Form 'Receive (incl. fees)' equals bridge 'Expected to receive' across both providers (Bungee, Near Intents) and all decimal precisions tested 2. Form 'Min. to receive' equals bridge 'Min. to receive' 3. No mismatch between summary and breakdown at any decimal precision (USDC 6 -> DAI 18, USDC 6 -> SOL 9, USDC 6 -> BNB 18, USDC 6 -> BTC 8) | H33: Not Run
A34: CC-31 | B34: Cross-chain: calculation parity - bridge 'Min. to deposit' equals swap 'Min. to receive' | C34: High | D34: Functional | E34: Cross-chain swap configured; both Bungee and Near Intents routes available | F34: 1. Configure Arb USDC -> Base DAI (Bungee); expand route panel 2. Read swap leg 'Min. to receive' and bridge leg 'Min. to deposit' 3. Verify they are equal 4. Repeat for Arb USDC -> SOL (Near Intents) and Arb USDC -> BNB (Near Intents) 5. Verify equality across decimals (USDC 6 -> DAI 18 / SOL 9 / BNB 18 / BTC 8) | G34: 1. Bridge 'Min. to deposit' equals swap 'Min. to receive' exactly (handoff value between legs) 2. Holds across both providers and all decimal precisions 3. If unequal, classify as defect: handoff mismatch could trap funds at intermediate hop | H34: Not Run
A35: CC-36 | B35: Cross-chain: BTC vs Solana destination - flow differences and shared gating | C35: High | D35: Functional | E35: Both BTC and Solana available as destination chains (Near Intents) | F35: 1. Run a full Solana destination flow (recipient required, base58 validation, checkbox required) 2. Run a full BTC destination flow (recipient required, bech32/legacy validation, checkbox required) 3. For each: try invalid format (EVM 0x, testnet tb1 for BTC on mainnet, malformed base58) 4. Check decimal precision of destination amounts (SOL 9, BTC 8) 5. Submit successful orders for both; verify TX/intent tracking and explorer links | G35: Shared: - Both require recipient (no default); both require network-confirmation checkbox - Both route via Near Intents only (Bungee unavailable) - Both show 'Modified recipient address to' banner on swap leg (no Account Proxy) Differences: - Solana: base58 (32-44 chars, no 0/O/I/l); rejects 0x; SOL has 9 decimals - BTC: bech32 (bc1q...) or legacy (1.../3...); rejects 0x and testnet tb1 on mainnet; BTC has 8 decimals; irreversibility warning more prominent - Status tracking: Solana -> Solana explorer (e.g. solscan); BTC -> Bitcoin explorer (e.g. blockstream); neither uses Etherscan for destination leg | H35: Not Run | I35: Use this case to ensure consistency in gating UX between BTC and Solana flows while accounting for address-format and explorer differences.

Sheet UIUX
A1: UI / UX Tests
A2: CoW Swap | swap.cow.fi | UIUX
A4: ID | B4: Test Name | C4: Priority | D4: Type | E4: Preconditions | F4: Test Steps | G4: Expected Result | H4: Status | I4: Notes / Defect ID
A5: UI-01 | B5: Page loads within 3 seconds | C5: High | D5: Performance | E5: Standard broadband connection | F5: 1. Open swap.cow.fi in fresh browser tab 2. Measure load time | G5: Swap UI interactive within 3 seconds | H5: Not Run
A6: UI-02 | B6: Mobile responsive layout | C6: High | D6: UI | E6: Mobile browser or DevTools mobile emulation | F6: 1. Open swap.cow.fi on 375px wide viewport 2. Navigate all tabs | G6: 1. All elements readable 2. no horizontal scroll 3. buttons tappable | H6: Not Run
A7: UI-03 | B7: Dark mode rendering | C7: Low | D7: UI | E7: OS dark mode enabled | F7: 1. Load site with system dark mode 2. Toggle manually if available | G7: No unreadable white-on-white or black-on-black text | H7: Not Run
A8: UI-04 | B8: Order tabs navigation (Swap/Limit/TWAP) | C8: Medium | D8: UI | F8: 1. Click each tab in order 2. Verify correct panel loads | G8: 1. Correct order form shown per tab 2. no content bleed between tabs | H8: Not Run
A9: UI-05 | B9: Token search & selection | C9: High | D9: Functional | E9: Token selector open | F9: 1. Click sell/buy token 2. Type token name or address 3. Select result | G9: 1. Correct token found via name and contract address 2. icon displayed | H9: Not Run
A10: UI-06 | B10: Swap direction toggle (flip) | C10: Medium | D10: Functional | E10: Both tokens selected | F10: 1. Click the swap-direction arrow between tokens | G10: 1. Sell/buy tokens swapped 2. amounts recalculated correctly | H10: Not Run
A11: UI-07 | B11: Transaction receipt links to explorer | C11: Low | D11: UI | E11: Swap completed | F11: 1. Click tx hash in order history | G11: Opens correct block explorer for current network | H11: Not Run
A12: UI-08 | B12: Error state: wallet not connected | C12: Medium | D12: Negative | E12: No wallet connected | F12: 1. Try to interact with swap form without connecting wallet | G12: 1. 'Connect Wallet' CTA shown 2. helpful message displayed | H12: Not Run
A13: UI-09 | B13: Header: CoW Swap logo navigates to home / swap form | C13: Medium | D13: Functional | E13: Any page of swap.cow.fi open | F13: 1. Navigate to a sub-page (e.g. /account) 2. Click the CoW Swap logo in the header | G13: 1. Navigates to the main swap form (/#/swap or root) 2. page loads without errors | H13: Not Run
A14: UI-10 | B14: Header: all navigation links open correct destinations | C14: Medium | D14: Functional | E14: swap.cow.fi open in browser; check each header link | F14: 1. Click each header navigation link in turn: Swap, Limit, Advanced (TWAP), Account 2. For any external links in the header (e.g. Docs, Blog, Stats): click and verify destination opens in a new tab | G14: 1. Each internal link navigates to the correct page/tab within the app 2. external links open in a new tab 3. no 404s or broken destinations 4. active link highlighted correctly for current page | H14: Not Run | I14: Cross-chain swap is accessed from within the Swap form (token selector), not via a dedicated header link.
A15: UI-11 | B15: Header: Settings (gear) icon opens settings modal | C15: Medium | D15: Functional | E15: swap.cow.fi open | F15: 1. Click the gear/settings icon in the header 2. Observe modal content | G15: Settings modal opens Settings are opened on every form (swap/limit/twap/hooks) | H15: Not Run
A16: UI-12 | B16: Header: layout correct and no overflow at 1280px and 1920px desktop widths | C16: Low | D16: UI | E16: Desktop browser | F16: 1. Set viewport to 1280px wide → inspect header 2. Set viewport to 1920px wide → inspect header | G16: 1. Header items correctly laid out at both widths 2. no text or icon overflow 3. logo, nav links, and wallet button all visible and aligned | H16: Not Run
A17: UI-13 | B17: Footer: all links open correct destinations | C17: Medium | D17: Functional | E17: swap.cow.fi open; scroll to footer | F17: 1. Locate the footer section 2. Click each link: 3. Verify each destination | G17: 1. All footer links open the correct external destination in a new tab 2. no broken or dead links | H17: Not Run | I17: Check both social links and legal/docs links
A18: UI-14 | B18: Footer: version / build info displayed | C18: Low | D18: UI | E18: swap.cow.fi open | F18: 1. Scroll to footer 2. Look for app version, build hash, or similar build info | G18: 1. App version or commit hash shown in footer 2. useful for bug reporting | H18: Not Run
A19: UI-15 | B19: Mobile (375px — iPhone SE): swap form fully functional | C19: High | D19: UI | E19: Browser DevTools mobile emulation or real device; viewport 375×667px | F19: 1. Open swap.cow.fi at 375px viewport width 2. Verify swap form visible and usable: token selectors, amount inputs, Swap button, settings icon 3. Connect wallet (if supported) 4. Open token selector modal — verify scrollable and searchable 5. Navigate to Limit and TWAP tabs | G19: 1. All form elements fit within 375px without horizontal scroll 2. inputs tappable with no overlap 3. token selector modal fills screen correctly 4. tab navigation works 5. no text truncation that hides critical information | H19: Not Run | I19: Primary mobile breakpoint. Already partially covered by UI-02 (375px check) — this test is more thorough.
A20: UI-16 | B20: Mobile (390px — iPhone 14): layout and touch targets | C20: Medium | D20: UI | E20: Viewport 390×844px (iPhone 14 / 15 size) | F20: 1. Open at 390px width 2. Check all buttons have sufficient tap target size (≥ 44px) 3. Scroll through the full page 4. Open and close modals (settings, token selector, confirm) | G20: 1. All interactive elements have adequate tap target size 2. no elements clipped by viewport 3. modals open and close correctly 4. scrolling smooth with no content cut off | H20: Not Run
A21: UI-17 | B21: Tablet (768px — iPad portrait): layout transitions correctly from mobile | C21: Medium | D21: UI | E21: Viewport 768×1024px (iPad portrait) | F21: 1. Open swap.cow.fi at 768px width 2. Check swap form layout 3. Check header — verify whether mobile hamburger or full nav shown 4. Navigate all main tabs (Swap, Limit, TWAP, Cross-chain, Account) 5. Verify orders table layout | G21: 1. Layout transitions cleanly from mobile to tablet breakpoint 2. swap form well-proportioned at 768px 3. header shows appropriate navigation for this width 4. no layout breaking, overlapping elements, or unexpected whitespace | H21: Not Run
A22: UI-18 | B22: Tablet (1024px — iPad landscape / small laptop): layout at mid-width | C22: Low | D22: UI | E22: Viewport 1024×768px | F22: 1. Open at 1024px width 2. Check swap form, header, footer, and orders table 3. Verify sidebar or two-column layout if applicable | G22: 1. Content fills the 1024px width appropriately 2. no excessive whitespace or cramped elements 3. full desktop navigation visible | H22: Not Run
A23: UI-19 | B23: Browser: Chrome (latest stable) — full functionality | C23: High | D23: Compatibility | E23: Chrome latest stable; MetaMask or other wallet extension installed | F23: 1. Open swap.cow.fi in Chrome 2. Connect wallet 3. Place a market swap order 4. Navigate all major sections (Swap, Limit, Account) | G23: 1. All functionality works correctly 2. no errors related to browser compatibility | H23: Not Run | I23: Primary supported browser — baseline for all other tests
A24: UI-20 | B24: Browser: Firefox (latest stable) — full functionality | C24: High | D24: Compatibility | E24: Firefox latest stable; wallet extension installed (MetaMask for Firefox) | F24: 1. Open swap.cow.fi in Firefox 2. Connect wallet 3. Place a swap order 4. Check token selector, modals, animations | G24: 1. All core functionality works in Firefox 2. no layout breakages specific to Firefox 3. wallet connection works via injected provider | H24: Not Run
A25: UI-21 | B25: Browser: Safari (latest stable, macOS) — full functionality | C25: High | D25: Compatibility | E25: Safari latest stable on macOS; wallet via WalletConnect or browser extension | F25: 1. Open swap.cow.fi in Safari 2. Connect wallet (WalletConnect or MetaMask if available) 3. Interact with swap form 4. Check for Safari-specific rendering issues (fonts, flex layout, animations) | G25: 1. App loads and functions correctly in Safari 2. no WebKit-specific layout bugs 3. wallet connection works 4. no issues with Safari's stricter localStorage/cookie policies | H25: Not Run | I25: Safari has stricter privacy settings — check for storage access issues
A26: UI-22 | B26: Browser: Safari on iOS (mobile) — full functionality | C26: High | D26: Compatibility | E26: iPhone with Safari (latest iOS); WalletConnect-compatible wallet app installed | F26: 1. Open swap.cow.fi in iOS Safari 2. Connect via WalletConnect deep-link 3. Interact with swap form at mobile viewport 4. Check for iOS Safari quirks: input zoom on focus, bottom bar overlap, safe-area insets | G26: 1. App usable in iOS Safari 2. inputs do not zoom on tap (font-size ≥ 16px or zoom disabled) 3. no content hidden behind iOS browser chrome / home indicator 4. WalletConnect deep-link launches wallet app correctly | H26: Not Run | I26: iOS Safari is the only browser engine on iPhone — critical coverage
A27: UI-23 | B27: Browser: Brave — no ad-blocking interference with app functionality | C27: Medium | D27: Compatibility | E27: Brave browser with default shields enabled; wallet extension installed | F27: 1. Open swap.cow.fi in Brave with shields up (default settings) 2. Check whether any requests are blocked that break functionality 3. Connect wallet and attempt a swap 4. Check for blocked RPC calls, analytics, or CDN resources | G27: 1. Core swap functionality works with Brave shields at default settings 2. if shields block non-critical analytics that is acceptable 3. if shields block RPC or price feed calls the app should degrade gracefully with an informative error rather than a blank/broken state | H27: Not Run

Sheet Hooks
A1: Hooks Tests
A2: CoW Swap | swap.cow.fi | Hooks
A4: ID | B4: Test Name | C4: Priority | D4: Type | E4: Preconditions | F4: Test Steps | G4: Expected Result | H4: Status | I4: Notes / Defect ID
A5: HK-01 | B5: Enable Hooks via settings toggle | C5: High | D5: Functional | E5: Wallet connected on a supported chain (Hooks not available for ETH-flow, Limit, TWAP tabs) | F5: 1. Open swap.cow.fi on the Swap tab 2. Click the Settings (gear) icon 3. Locate the 'Hooks' toggle 4. Enable Hooks 5. Close settings 6. Verify Hooks tab/option is now visible in the swap form | G5: 1. Hooks enabled 2. Hooks section or tab appears in the swap UI 3. setting persists on page refresh | H5: Not Run | I5: Per spec: 'Enable Hooks tab to place orders with Pre-Post iterations'. Hooks NOT available on ETH-flow, Limit, or TWAP tabs Hooks are not avaible in the CoW Widget
A6: HK-02 | B6: Hooks not available on ETH-flow | C6: High | D6: Functional | E6: Hooks enabled in settings; ETH selected as sell token (ETH-flow active) | F6: 1. Enable Hooks in settings 2. Select ETH as sell token 3. Check whether Hooks tab/option is visible or accessible | G6: Error message is displayed, a user cannot place an order | H6: Not Run
A7: HK-03 | B7: Add a Pre-hook to a swap order | C7: High | D7: Functional | E7: Hooks enabled; ERC-20 tokens selected | F7: 1. Open Hooks section 2. Click 'Add Pre-hook' 3. Select or configure a pre-hook action (e.g. token approval dApp) 4. Confirm hook configuration 5. Place swap order | G7: 1. Pre-hook appears in hooks list 2. order placed with pre-hook attached 3. pre-hook executes before swap in settlement | H7: Not Run
A8: HK-04 | B8: Add a Post-hook to a swap order | C8: High | D8: Functional | E8: Hooks enabled; | F8: 1. Open Hooks section 2. Click 'Add Post-hook' 3. Configure a post-hook action 4. Place swap order | G8: 1. Post-hook appears in hooks list 2. executes after swap in settlement batch | H8: Not Run
A9: HK-05 | B9: Remove a hook before placing order | C9: Medium | D9: Functional | E9: One or more hooks configured | F9: 1. Add a hook (pre or post) 2. Click remove/delete on the hook 3. Confirm removal | G9: 1. Hook removed from list 2. order can proceed without it 3. no residual hook state | H9: Not Run
A10: HK-06 | B10: Hooks section shows correct gas estimate impact | C10: Medium | D10: Functional | E10: Hooks enabled; pre or post hook configured | F10: 1. Add a hook with known gas cost 2. Observe Network costs (est.) field | G10: 1. Network costs updated to include hook gas overhead 2. tooltip breakdown reflects hook cost | H10: Not Run
A11: HK-07 | B11: Disable Hooks — section disappears from form | C11: Medium | D11: Functional | E11: Hooks currently enabled | F11: 1. Open Settings on Swap or Hooks tabs 2. Disable the Hooks toggle 3. Return to swap form | G11: 1. Hooks section no longer visible in swap form 2. any previously configured hooks cleared or hidden | H11: Not Run

Sheet RWA
A1: RWA (Ondo & xStocks) Tests
A2: CoW Swap | swap.cow.fi | RWA (Ondo Global Markets + Backed xStocks)
A4: ID | B4: Test Name | C4: Priority | D4: Type | E4: Preconditions | F4: Test Steps | G4: Expected Result | H4: Status | I4: Notes / Defect ID
A5: RW-01 | B5: RWA token availability — Ethereum Mainnet (chainId 1) lists Ondo + xStocks | C5: High | D5: Functional | E5: Wallet connected on Ethereum Mainnet; token search opened use is on a supported location | F5: 1. Connect wallet on Ethereum Mainnet 2. Open token selector for sell or buy side 3. Search for an Ondo token (e.g. USDon, USDY) 4. Search for an xStocks token (e.g. AAPLx, NVDAx) | G5: 1. Ondo and xStocks tokens appear in the token list 2. Both lists are loaded as restricted/RWA token lists 3. Token logos and names render correctly | H5: Not Run
A6: RW-02 | B6: RWA token availability — BNB Smart Chain (chainId 56) lists Ondo + xStocks | C6: High | D6: Functional | E6: Wallet connected on BNB Smart Chain user is on a supported location | F6: 1. Switch wallet/network to BNB Smart Chain 2. Open token selector 3. Search for an Ondo token 4. Search for an xStocks token | G6: 1. Both Ondo and xStocks tokens are available on BNB Chain 2. Lists are fetched per chain | H6: Not Run
A7: RW-03 | B7: RWA token availability — Arbitrum (chainId 42161) lists xStocks only (no Ondo) | C7: High | D7: Functional | E7: Wallet connected on Arbitrum One a user is on a supported location | F7: 1. Switch network to Arbitrum One 2. Open token selector 3. Search for an xStocks token (e.g. AAPLx) 4. Search for an Ondo token (e.g. USDY) | G7: 1. xStocks tokens are available 2. Ondo tokens are NOT shown in the token list for Arbitrum 3. No Ondo restriction is applied | H7: Not Run
A8: RW-04 | B8: RWA token availability — Ink (chainId 57073) lists xStocks only | C8: Medium | D8: Functional | E8: Wallet connected on Ink network a user is on a supported locaiton | F8: 1. Switch network to Ink 2. Open token selector 3. Search for xStocks and Ondo tokens | G8: 1. xStocks tokens available 2. Ondo tokens NOT available on Ink | H8: Not Run
A9: RW-05 | B9: RWA tokens NOT available on Gnosis/Polygon/Base/Avalanche/Plasma/Linea/Sepolia | C9: High | D9: Negative | E9: Wallet connected on Gnosis Chain (or Polygon, Base, Avalanche, Plasma, Linea, Sepolia) | F9: 1. Switch network to Gnosis (then repeat for Polygon, Base, Avalanche, Plasma, Linea, Sepolia) 2. Open token selector 3. Search for Ondo and xStocks tokens | G9: 1. Neither Ondo nor xStocks tokens appear on these chains 2. No RWA-related warnings/modals are triggered | H9: Not Run
A10: RW-06 | B10: Geo restriction — user country in blocked list cannot trade RWA token | C10: High | D10: Negative | E10: RWA geoblock feature flag enabled; Geo API returns a blocked country code (e.g. US, DE, CN); Ondo or xStocks token selected on a supported chain | F10: 1. Configure environment so geo API returns 'US' (or any blocked country) 2. Select USDY or AAPLx as buy/sell token 3. Attempt to place a swap, limit, or TWAP order | G10: 1. Trade form shows the 'RestrictedForCountry' validation 2. Place order button is disabled or shows a restriction message 3. No order request is submitted 4. Behavior is the same on Swap, Limit, and TWAP tabs | H10: Not Run
A11: RW-07 | B11: Geo restriction — blocked list coverage: US, Canada, China, Russia, all EU/EEA, sanctioned states | C11: High | D11: Functional | E11: RWA geoblock enabled; ability to spoof / vary geo response | F11: 1. For each country in the blocked list (AF, DZ, BY, CA, CN, CU, KP, ER, IR, LY, MM, MA, NP, RU, SO, SS, SD, SY, US, VE, AT, BE, BG, HR, CY, CZ, DK, EE, FI, FR, DE, GR, HU, IE, IT, LV, LT, LU, MT, NL, PL, PT, RO, SK, SI, ES, SE, IS, LI, NO): 2. Simulate geo API returning that country 3. Try to interact with an Ondo or xStocks token | G11: 1. Every country in the list triggers the Restricted state 2. Trade is blocked 3. Equivalent behavior for both Ondo and xStocks issuers (shared restriction list) | H11: Not Run
A12: RW-08 | B12: Geo allowed — user country NOT in blocked list can trade without consent modal | C12: High | D12: Positive | E12: RWA geoblock enabled; Geo API returns an allowed country (e.g. CH, GB, BR, JP, AU, AE) | F12: 1. Geo API returns 'CH' (Switzerland) or any non-blocked country 2. Select an Ondo / xStocks token 3. Enter a valid amount and request a quote | G12: 1. RwaTokenStatus = Allowed 2. No consent modal is shown 3. Quote loads and order can be placed normally | H12: Not Run
A13: RW-09 | B13: Consent modal — appears when geo country is unknown (VPN / privacy / API failure) | C13: High | D13: Functional | E13: RWA geoblock enabled; Geo API returns null country (loading, error, or VPN); no prior consent for this wallet+hash | F13: 1. Use a VPN or block geo API requests so country resolves to null 2. Connect wallet (record wallet address) 3. Select an Ondo or xStocks token | G13: 1. RwaConsentModal is shown 2. Title: 'Additional confirmation required for this token' (or '...token list' for list-level consent) 3. Body text mentions: 'We could not reliably determine your location (e.g., due to VPN or privacy settings)' 4. Lists required attestations: NOT a U.S. Person, NOT EU/EEA resident, NOT in sanctioned jurisdictions, NOT in a securities-prohibited jurisdiction 5. 'I Confirm' and 'Cancel' buttons are present | H13: Not Run
A14: RW-10 | B14: Consent — confirmed consent persists per wallet + consentHash (localStorage) | C14: High | D14: Functional | E14: Consent modal currently displayed for an Ondo/xStocks token; wallet is connected | F14: 1. Click 'I Confirm' in the consent modal 2. Verify localStorage key 'rwaConsentCache:v1' contains an entry for {wallet}-{ipfsHash} 3. Reload the page; select another RWA token from the same issuer 4. Disconnect and reconnect the same wallet, select RWA token again 5. Switch to a different wallet address and select the same RWA token | G14: 1. After confirm, modal closes and trade flow proceeds (RwaTokenStatus = ConsentIsSigned when country unknown) 2. localStorage entry persists across reloads 3. Reload — no consent modal for same wallet+hash 4. After reconnect — still no modal 5. Different wallet address — consent modal IS shown (consent is per-wallet) | H14: Not Run
A15: RW-11 | B15: Consent — 'Cancel' dismisses modal and blocks the trade | C15: Medium | D15: Negative | E15: Consent modal displayed; no prior consent record | F15: 1. Click 'Cancel' on the consent modal 2. Attempt to proceed with the trade | G15: 1. Modal closes 2. No consent is written to localStorage 3. Trade flow does not proceed (status remains RequiredConsent) 4. Re-selecting the RWA token re-opens the modal | H15: Not Run
A16: RW-12 | B16: Consent — consentHash change invalidates previous consent (terms update flow) | C16: Medium | D16: Functional | E16: Wallet has a valid consent for old hash stored in localStorage; CMS updates restricted token list with new RWA_CONSENT_HASH | F16: 1. Pre-populate rwaConsentCache:v1 with an entry for {wallet}-{oldHash} 2. Deploy/simulate a new RWA_CONSENT_HASH (different IPFS hash) 3. Select an RWA token while geo is unknown 4. Confirm the new modal 5. Inspect localStorage | G16: 1. Consent modal re-appears (old hash entry no longer matches current ipfsHash) 2. After Confirm, a new {wallet}-{newHash} entry is written 3. Old entry may remain but is unused | H16: Not Run | I16: Per RwaConsentKey type: { wallet, ipfsHash }. RWA_CONSENT_HASH is shared across all restricted issuers.
A17: RW-13 | B17: Validation — Swap form blocks xStocks trade below $10 USD minimum | C17: High | D17: Negative | E17: Wallet allowed (not restricted); Swap tab; xStocks token selected as input or output; USD fiat amount computed | F17: 1. Select e.g. AAPLx as input or output token on the Swap tab 2. Enter an amount whose USD value < $10 (e.g. $5) 3. Observe the trade form button 4. Increase amount above $10 and re-observe | G17: 1. Button shows 'Minimum trade size for xStocks tokens is $10' 2. Submit is disabled 3. After raising USD amount ≥ $10, validation clears and order can proceed | H17: Not Run | I17: for TWAP orders is 20 usd (10 use per part)
A18: RW-14 | B18: Validation — TWAP form blocks xStocks trade below $10 per PART | C18: High | D18: Negative | E18: TWAP tab; xStocks token in pair; valid number of parts configured | F18: 1. Open TWAP tab 2. Select an xStocks token as buy or sell 3. Configure parts=10 and a total USD amount such that per-part USD < $10 (e.g. total $50, parts=10 → $5/part) 4. Observe primary action button 5. Reduce parts so per-part ≥ $10 and re-check | G18: 1. Button shows 'Minimum trade size for xStocks tokens is $10 per part' 2. Submit is disabled 3. Lowering parts so per-part ≥ $10 clears the validation | H18: Not Run
A19: RW-15 | B19: Min trade — Ondo tokens are NOT subject to the $10 minimum | C19: Medium | D19: Positive | E19: Swap or Limit or TWAP; Ondo token (e.g. USDY) selected; small USD amount | F19: 1. Select USDY as input or output 2. Enter a USD amount below $10 3. Submit the order | G19: 1. No XstockMinimumTradeSize validation triggers 2. Order can proceed (assuming other validations pass) 3. The $10 floor applies ONLY to xStocks (Backed Finance) tokens | H19: Not Run
A20: RW-16 | B20: Trading hours — xStocks trades outside US market hours: no UI block, solver/quote behavior | C20: Medium | D20: Functional | E20: xStocks pair selected (e.g. AAPLx); current time outside Nasdaq/NYSE regular hours (e.g. weekend or 02:00 UTC weekday) | F20: 1. Set system / observe real time outside US equity market hours 2. Select an xStocks token and enter ≥ $10 USD amount 3. Request a quote (Swap, Limit, TWAP) 4. Observe quote response and place-order flow | G20: 1. The frontend does NOT have an explicit trading-hours validation 2. Behavior depends on solver/issuer (Backed): quote may return NoLiquidity / unavailable; or quote returns but settles only when market opens 3. Any returned error message is user-readable; if no quote, the standard 'No quote available' state is shown | H20: Not Run
A21: RW-17 | B21: Trading hours —Ondo - weekends | C21: Medium | D21: Functional | E21: Connect to a wallet on an available location pick an onde token to trade | F21: 1. Specify a date and time corresponds to a Saturday and Sunday 2. check the form | G21: 1. Error message appears that tokens are not tradeable till Sunday 23.59 | H21: Not Run
A22: RW-18 | B22: Mixed pair — only one side is RWA still triggers RWA checks | C22: High | D22: Functional | E22: Wallet connected; pair where exactly one token is Ondo/xStocks (e.g. WETH → AAPLx) | F22: 1. Select WETH as sell token, AAPLx as buy token 2. Verify RWA checks apply 3. Reverse to AAPLx → USDC and verify 4. Try a fully non-RWA pair (WETH → USDC) and verify no RWA logic runs | G22: 1. With any RWA token on either side, useAnyRestrictedToken returns the RWA token and RWA flow engages 2. Non-RWA pair: no consent / geo check 3. xStocks $10 min still applies when xStocks present on either side | H22: Not Run
